{
  "p": {
    "value": [
      929.0,
      926.0,
      925.0,
      921.0,
      909.0,
      903.0,
      892.0,
      879.0,
      862.0,
      851.0,
      850.0,
      837.0,
      829.0,
      805.0,
      795.0,
      769.0,
      760.0,
      752.0,
      744.0,
      726.0,
      719.0,
      703.0,
      700.0,
      687.0,
      679.0,
      669.0,
      660.0,
      651.0,
      636.0,
      620.0,
      610.0,
      604.0,
      597.0,
      590.0,
      585.0,
      582.0,
      579.0,
      570.0,
      561.0,
      556.0,
      555.0,
      552.0,
      547.0,
      546.0,
      539.0,
      532.0,
      526.0,
      524.0,
      514.0,
      513.0,
      512.0,
      501.0,
      500.0,
      488.0,
      475.0,
      469.0,
      463.0,
      459.0,
      452.0,
      440.0,
      435.0,
      427.0,
      426.0,
      419.0,
      418.0,
      412.0,
      410.0,
      408.0,
      407.0,
      404.0,
      400.0,
      397.0,
      396.0,
      367.0,
      355.0,
      337.0,
      332.0,
      330.0,
      328.0,
      319.0,
      318.0,
      316.0,
      311.0,
      305.0,
      300.0,
      295.0,
      291.0,
      281.0,
      280.0,
      276.0,
      272.0,
      266.0,
      263.0,
      260.0,
      254.0,
      250.0,
      248.0,
      242.0,
      233.0,
      232.0,
      230.0,
      221.0,
      220.0,
      218.0,
      211.0,
      210.0,
      204.0,
      200.0,
      196.0,
      191.0,
      184.0,
      181.0,
      179.0,
      175.0,
      170.0,
      165.0,
      163.0,
      160.0,
      155.0,
      154.0,
      150.0,
      145.0,
      144.0,
      138.0,
      133.0,
      131.0,
      125.0,
      119.0,
      116.0,
      115.0,
      114.0,
      113.0,
      111.0,
      108.0,
      103.0,
      100.0,
      98.4,
      98.1
    ],
    "unit": "hectopascal"
  },
  "z": {
    "value": [
      697,
      727,
      737,
      776,
      896,
      956,
      1068,
      1202,
      1379,
      1496,
      1507,
      1641,
      1725,
      1980,
      2089,
      2378,
      2481,
      2573,
      2666,
      2879,
      2963,
      3159,
      3196,
      3351,
      3447,
      3570,
      3681,
      3795,
      3987,
      4197,
      4331,
      4413,
      4509,
      4606,
      4675,
      4716,
      4757,
      4883,
      5009,
      5080,
      5095,
      5138,
      5210,
      5224,
      5326,
      5430,
      5520,
      5550,
      5702,
      5717,
      5733,
      5904,
      5920,
      6110,
      6322,
      6422,
      6523,
      6590,
      6708,
      6915,
      7002,
      7145,
      7163,
      7288,
      7307,
      7416,
      7453,
      7490,
      7509,
      7565,
      7640,
      7696,
      7715,
      8275,
      8519,
      8902,
      9010,
      9054,
      9097,
      9296,
      9318,
      9363,
      9476,
      9613,
      9730,
      9847,
      9943,
      10187,
      10212,
      10311,
      10412,
      10565,
      10643,
      10722,
      10882,
      10990,
      11044,
      11210,
      11466,
      11495,
      11553,
      11820,
      11851,
      11911,
      12128,
      12159,
      12350,
      12480,
      12611,
      12778,
      13020,
      13126,
      13196,
      13339,
      13523,
      13712,
      13789,
      13907,
      14106,
      14146,
      14310,
      14520,
      14563,
      14824,
      15050,
      15142,
      15425,
      15720,
      15873,
      15925,
      15977,
      16029,
      16136,
      16300,
      16583,
      16760,
      16856,
      16874
    ],
    "unit": "meter"
  },
  "T": {
    "value": [
      42.2,
      41.2,
      40.8,
      40.3,
      38.9,
      38.2,
      36.9,
      35.2,
      33.1,
      31.7,
      31.6,
      30.3,
      29.5,
      27.0,
      25.9,
      23.1,
      22.1,
      21.2,
      20.4,
      18.3,
      17.5,
      15.6,
      15.2,
      13.7,
      12.8,
      11.6,
      10.5,
      9.4,
      7.6,
      5.5,
      4.2,
      3.5,
      2.5,
      1.6,
      1.1,
      0.8,
      0.4,
      -0.7,
      -1.6,
      -2.2,
      -2.3,
      -2.2,
      -1.9,
      -1.9,
      -2.4,
      -2.9,
      -3.3,
      -3.1,
      -2.1,
      -2.1,
      -2.2,
      -3.8,
      -3.9,
      -5.5,
      -7.4,
      -8.2,
      -9.1,
      -9.7,
      -10.7,
      -12.5,
      -13.3,
      -14.5,
      -14.6,
      -15.4,
      -15.5,
      -15.3,
      -15.3,
      -15.3,
      -15.3,
      -15.6,
      -16.1,
      -16.3,
      -16.4,
      -20.9,
      -22.9,
      -25.9,
      -26.9,
      -27.3,
      -27.7,
      -29.3,
      -29.4,
      -29.7,
      -30.7,
      -32.0,
      -33.1,
      -33.9,
      -34.5,
      -36.1,
      -36.3,
      -36.9,
      -37.5,
      -38.4,
      -38.9,
      -39.3,
      -40.3,
      -40.7,
      -41.0,
      -41.9,
      -43.3,
      -43.5,
      -43.9,
      -45.2,
      -45.3,
      -45.7,
      -47.3,
      -47.5,
      -48.7,
      -49.5,
      -50.5,
      -51.7,
      -53.5,
      -54.1,
      -54.5,
      -55.3,
      -56.3,
      -57.4,
      -57.8,
      -58.5,
      -59.5,
      -59.8,
      -60.9,
      -62.1,
      -62.3,
      -63.8,
      -65.1,
      -65.7,
      -67.7,
      -68.9,
      -69.3,
      -69.5,
      -69.5,
      -69.3,
      -68.9,
      -68.1,
      -69.2,
      -69.9,
      -70.1,
      -70.1
    ],
    "unit": "degree_Celsius"
  },
  "Td": {
    "value": [
      4.2,
      0.2,
      -0.2,
      -0.2,
      -0.0,
      0.0,
      0.1,
      0.3,
      0.5,
      0.6,
      0.6,
      0.5,
      0.4,
      0.2,
      0.1,
      -0.1,
      -0.2,
      -0.3,
      -0.4,
      -0.5,
      -0.6,
      -0.8,
      -0.8,
      -1.3,
      -1.6,
      -2.0,
      -2.4,
      -2.8,
      -3.4,
      -4.1,
      -4.5,
      -4.8,
      -5.1,
      -5.4,
      -5.3,
      -5.2,
      -5.6,
      -6.7,
      -8.2,
      -9.1,
      -9.3,
      -12.2,
      -16.9,
      -17.9,
      -20.5,
      -23.1,
      -25.3,
      -29.2,
      -49.1,
      -50.1,
      -49.7,
      -45.3,
      -44.9,
      -43.4,
      -41.7,
      -40.9,
      -40.1,
      -41.7,
      -41.2,
      -40.4,
      -40.1,
      -39.5,
      -39.7,
      -41.3,
      -41.5,
      -51.1,
      -54.3,
      -55.0,
      -55.3,
      -55.6,
      -56.1,
      -56.3,
      -56.4,
      -59.0,
      -60.1,
      -61.9,
      -62.9,
      -63.3,
      -63.5,
      -64.3,
      -64.4,
      -64.7,
      -65.4,
      -66.3,
      -67.1,
      -67.6,
      -68.1,
      -69.2,
      -69.3,
      -69.9,
      -70.3,
      -71.0,
      -71.3,
      -71.6,
      -72.3,
      -72.7,
      -72.9,
      -73.5,
      -74.4,
      -74.5,
      -74.9,
      -76.2,
      -76.3,
      -76.5,
      -77.3,
      -77.4,
      -78.1,
      -78.5,
      -79.2,
      -80.2,
      -81.5,
      -82.1,
      -82.3,
      -82.8,
      -83.3,
      -83.9,
      -84.1,
      -84.5,
      -85.5,
      -85.8,
      -86.9,
      -87.1,
      -87.3,
      -88.2,
      -89.1,
      -89.7,
      -91.7,
      -91.9,
      -92.3,
      -92.5,
      -93.5,
      -93.3,
      -92.9,
      -92.1,
      -92.6,
      -92.9,
      -93.1,
      -93.1
    ],
    "unit": "degree_Celsius"
  },
  "u": {
    "value": [
      -2.394141003279682,
      1.7364817766693048,
      3.7622215765823555,
      2.588190451025208,
      5.13030214988503,
      6.498382723187705,
      7.184510449591888,
      6.339273926110489,
      8.000000000000002,
      6.761892187851188,
      7.184510449591888,
      5.4723222932106985,
      2.4310744873370265,
      9.000000000000002,
      8.000000000000002,
      7.000000000000002,
      8.35623892592501,
      9.192388155425117,
      7.778174593052022,
      5.500000000000001,
      5.735764363510461,
      10.64897657575689,
      12.124355652982137,
      7.071067811865475,
      7.4564936725636,
      6.309340799861507,
      7.778174593052022,
      7.070663706551931,
      6.4278760968653925,
      5.494037402629091,
      8.35623892592501,
      5.000000000000001,
      5.000000000000001,
      3.942047444998305,
      2.8470094961277286,
      5.071419140888391,
      7.4564936725636,
      8.48528137423857,
      9.010672487178907,
      8.030070108914646,
      8.228993532094622,
      8.999026535611549,
      8.48528137423857,
      7.872708347886085,
      2.0705523608201664,
      3.7622215765823555,
      6.691306063588582,
      6.894399988070801,
      6.784384769251408,
      6.857338405616897,
      6.928203230275507,
      5.4378467222199,
      5.4378467222199,
      5.977168188550474,
      7.2504622962932,
      8.693332436601615,
      8.606742803667318,
      9.510565162951535,
      9.396926207859085,
      5.142300877492314,
      6.553216354311933,
      7.912737803725163,
      7.778174593052022,
      10.72462220366569,
      11.03215055049411,
      11.78200123147645,
      11.583084814448782,
      11.258330249197698,
      11.370056192812147,
      13.594616805549752,
      13.594616805549752,
      14.5009245925864,
      14.5009245925864,
      15.320888862379558,
      19.6596490629358,
      20.982940959338205,
      21.44924440733138,
      22.06430110098822,
      23.755409284380757,
      22.936257240091763,
      22.936257240091763,
      23.755409284380757,
      24.57456132866975,
      25.114736709748712,
      23.382685902179837,
      22.65769467591625,
      22.65769467591625,
      27.03201746153672,
      27.35823989431638,
      30.61168974987886,
      33.53338812035605,
      36.37306695894641,
      36.252311481466,
      37.158619268502655,
      38.84969408579279,
      39.83716857408417,
      42.43524478543748,
      46.765371804359674,
      47.63139720814411,
      47.63139720814411,
      48.10408389266678,
      51.659543861089055,
      51.659543861089055,
      52.5658516481257,
      48.978703599806174,
      48.49742261192855,
      51.961524227066306,
      53.69357503463518,
      53.69357503463518,
      53.69357503463518,
      51.961524227066306,
      52.82754963085074,
      53.69357503463518,
      55.28477500923565,
      52.5658516481257,
      50.7532360740524,
      51.659543861089055,
      49.00535883036023,
      46.35484447838799,
      45.03332099679079,
      46.22169713886915,
      42.011119192374075,
      41.34647531457997,
      34.76862696907861,
      34.60542105377949,
      33.80740392011739,
      32.88924172750679,
      33.48346360241507,
      32.874425037027606,
      31.878230338935857,
      31.878230338935857,
      30.882035640844112,
      26.89725684847713,
      21.9162833580184,
      15.40723237962305,
      17.202192930068822,
      19.052558883257646,
      19.241633557066713
    ],
    "unit": "knot"
  },
  "v": {
    "value": [
      6.5778483455013586,
      9.84807753012208,
      10.336618828644992,
      9.659258262890683,
      14.095389311788626,
      17.85415979493226,
      15.40723237962305,
      13.594616805549752,
      13.856406460551018,
      14.5009245925864,
      15.40723237962305,
      15.035081932574535,
      13.787308542170912,
      15.588457268119894,
      13.856406460551018,
      12.12435565298214,
      9.958577760546714,
      9.19238815542512,
      7.778174593052024,
      9.526279441628825,
      8.191520442889917,
      7.456493672563603,
      7.000000000000006,
      7.071067811865477,
      10.648976575756894,
      9.01067248717891,
      7.778174593052024,
      8.426488874308758,
      7.66044443118978,
      11.78200123147645,
      9.958577760546714,
      8.660254037844386,
      8.660254037844386,
      10.269384691469218,
      10.62518408917975,
      10.8756934444398,
      10.648976575756894,
      8.485281374238571,
      6.30934079986151,
      11.468128620045885,
      11.326237921249266,
      10.724622203665692,
      8.485281374238571,
      9.056514962673266,
      7.7274066103125465,
      10.336618828644992,
      7.431448254773942,
      5.7850884871788555,
      4.23935411386564,
      4.120304599280436,
      4.0000000000000036,
      2.5357095704441948,
      2.5357095704441948,
      -0.5229344564859473,
      3.3809460939255933,
      2.3293714059226858,
      2.631345342504634,
      3.0901699437494754,
      3.4202014332566852,
      6.128355544951824,
      4.588611490808371,
      7.64124207504897,
      7.778174593052024,
      8.999026535611552,
      8.619260654559213,
      5.494037402629089,
      5.9018764966141095,
      6.500000000000005,
      6.302525063202379,
      6.339273926110487,
      6.339273926110487,
      6.761892187851187,
      6.761892187851187,
      12.85575219373079,
      13.765834472425112,
      16.991650558345622,
      17.998053071223104,
      17.238521309118426,
      16.633716654180343,
      16.0601402178293,
      16.0601402178293,
      16.633716654180343,
      17.20729309053139,
      14.500000000000012,
      13.500000000000012,
      10.56545654351748,
      10.56545654351748,
      18.92802239958453,
      18.453365814534635,
      16.968336708621788,
      15.636875684405869,
      21.000000000000018,
      16.904730469627967,
      17.327348731368666,
      20.65674876257919,
      23.00000000000002,
      24.50000000000002,
      27.000000000000025,
      27.500000000000025,
      27.500000000000025,
      26.664529113548525,
      24.08924091921985,
      24.08924091921985,
      24.511859180960553,
      27.149338733794863,
      28.000000000000025,
      30.00000000000003,
      31.00000000000003,
      31.00000000000003,
      31.00000000000003,
      30.00000000000003,
      30.50000000000003,
      31.00000000000003,
      25.779713966182648,
      24.511859180960553,
      23.666622657479152,
      24.08924091921985,
      24.969477485675082,
      25.694909873055853,
      26.00000000000002,
      21.553531348775657,
      16.126557729538533,
      15.048886306329416,
      12.654745303049737,
      9.922944809411959,
      9.058666578588221,
      11.9707050163984,
      5.904038040675632,
      2.876139510672722,
      2.788983767925064,
      2.788983767925064,
      2.701828025177406,
      2.353205054186773,
      1.9174263404484815,
      7.184510449591886,
      12.045105163371973,
      11.00000000000001,
      10.66581164541941
    ],
    "unit": "knot"
  },
  "site_info": {
    "site-id": "KVEF",
    "site-name": "LAS VEGAS",
    "site-lctn": "NV US",
    "site-latlon": [
      36.05,
      -115.18
    ],
    "site-elv": 697.0,
    "source": "RAOB OBSERVED PROFILE",
    "model": "no-model",
    "fcst-hour": "no-fcst-hour",
    "run-time": [
      "none",
      "none",
      "none",
      "none"
    ],
    "valid-time": [
      2024,
      6,
      23,
      0
    ]
  },
  "titles": {
    "top_title": "RAOB OBSERVED VERTICAL PROFILE",
    "left_title": "VALID: 6-23-2024 0Z",
    "right_title": "KVEF - LAS VEGAS, NV US | 36.05, -115.18    "
  }
}