{"type":"FeatureCollection","features":[{"type":"Feature","geometry":{"type":"Point","coordinates":[-114.054333,36.906944]},"properties":{"id":73,"numid":2574,"stationid":2574,"name":"Town Wash","description":"Rain Gauge","in_service":1,"interval_data":"0.24","interval_time":43200,"novascore":1}},{"type":"Feature","geometry":{"type":"Point","coordinates":[-114.073056,36.799722]},"properties":{"id":81,"numid":2599,"stationid":2599,"name":"Town Wash Channel","description":"Water Level Float","in_service":1,"interval_data":"0.20","interval_time":43200,"novascore":1}},{"type":"Feature","geometry":{"type":"Point","coordinates":[-115.15975,36.293556]},"properties":{"id":1074,"numid":4569,"stationid":4569,"name":"Beltway Channel W. of Revere","in_service":1,"interval_data":"0.00","interval_time":43200,"novascore":1}},{"type":"Feature","geometry":{"type":"Point","coordinates":[-114.964078,36.083272]},"properties":{"id":414,"numid":4554,"stationid":4554,"name":"Lower C-1 Channel (USGS)","description":"C-1 Channel ABV Mouth 09419754","in_service":1,"interval_data":"0.28","interval_time":43200,"novascore":1}},{"type":"Feature","geometry":{"type":"Point","coordinates":[-114.765389,36.584778]},"properties":{"id":1050,"numid":3134,"stationid":3134,"name":"Moapa SW 1","description":"Rain Gauge","in_service":1,"interval_data":"0.39","interval_time":43200,"novascore":1}},{"type":"Feature","geometry":{"type":"Point","coordinates":[-114.781333,36.491111]},"properties":{"id":1064,"numid":3114,"stationid":3114,"name":"California Wash 4","description":"Weather Station","in_service":1,"interval_data":"0.35","interval_time":43200,"novascore":1}},{"type":"Feature","geometry":{"type":"Point","coordinates":[-114.856694,36.555528]},"properties":{"id":1056,"numid":3124,"stationid":3124,"name":"Moapa SW 3","description":"Weather Station","in_service":1,"interval_data":"0.43","interval_time":43200,"novascore":1}},{"type":"Feature","geometry":{"type":"Point","coordinates":[-114.85575,36.803917]},"properties":{"id":121,"numid":3234,"stationid":3234,"name":"Wildcat Wash - 5052 (HL)","description":"Rain Gauge","in_service":1,"interval_data":"0.16","interval_time":43200,"novascore":1}},{"type":"Feature","geometry":{"type":"Point","coordinates":[-114.62345,36.755358]},"properties":{"id":143,"numid":3384,"stationid":3384,"name":"Meadow Valley Wash","description":"Water Level Float","in_service":1,"interval_data":"0.16","interval_time":43200,"novascore":1}},{"type":"Feature","geometry":{"type":"Point","coordinates":[-115.316806,36.062222]},"properties":{"id":1035,"numid":4464,"stationid":4464,"name":"Hualapai at Maule (F-3) DB","description":"Water Level Bubbler","in_service":1,"interval_data":"0.28","interval_time":43200,"novascore":1}},{"type":"Feature","geometry":{"type":"Point","coordinates":[-115.214556,35.981917]},"properties":{"id":1084,"numid":4669,"stationid":4669,"name":"Central Duck Creek DB","description":"Water Level Bubbler","in_service":1,"interval_data":"M","interval_time":43200,"novascore":1}},{"type":"Feature","geometry":{"type":"Point","coordinates":[-115.116528,36.015972]},"properties":{"id":455,"numid":4714,"stationid":4714,"name":"Pittman Pecos","description":"Water Level Float","in_service":1,"interval_data":"0.35","interval_time":43200,"novascore":1}},{"type":"Feature","geometry":{"type":"Point","coordinates":[-115.195556,36.096111]},"properties":{"id":388,"numid":4479,"stationid":4479,"name":"Tropicana North Branch DB","description":"Water Level Bubbler","in_service":1,"interval_data":"0.43","interval_time":43200,"novascore":1}},{"type":"Feature","geometry":{"type":"Point","coordinates":[-115.503778,36.450917]},"properties":{"id":1095,"numid":3709,"stationid":3709,"name":"Lee Canyon 1","description":"Rain Gauge","in_service":1,"interval_data":"0.28","interval_time":43200,"novascore":1}},{"type":"Feature","geometry":{"type":"Point","coordinates":[-115.5428,35.47149]},"properties":{"id":1099,"numid":9008,"stationid":9008,"name":"Mountain Pass  (San Bernardino)","description":"Rain Gauge","in_service":1,"interval_data":"0.48","interval_time":43200,"novascore":1}},{"type":"Feature","geometry":{"type":"Point","coordinates":[-115.319389,36.247583]},"properties":{"id":1110,"numid":4264,"stationid":4264,"name":"Beltway at Lone Mtn DB","description":"Water Level Bubbler","in_service":1,"interval_data":"0.71","interval_time":43200,"novascore":1}},{"type":"Feature","geometry":{"type":"Point","coordinates":[-114.953472,36.802333]},"properties":{"id":1107,"numid":3229,"stationid":3229,"name":"Coyote Springs DB","description":"Water Level Bubbler","in_service":1,"interval_data":"0.20","interval_time":43200,"novascore":1}},{"type":"Feature","geometry":{"type":"Point","coordinates":[-115.119014,36.12295]},"properties":{"id":309,"numid":4374,"stationid":4374,"name":"Flamingo Wash at Eastern Ave.","description":"Water Level Float","in_service":1,"interval_data":"0.16","interval_time":43200,"novascore":1}},{"type":"Feature","geometry":{"type":"Point","coordinates":[-114.093611,36.826111]},"properties":{"id":86,"numid":2684,"stationid":2684,"name":"Abbott Wash DB","description":"Water Level Float","in_service":1,"interval_data":"0.20","interval_time":43200,"novascore":1}},{"type":"Feature","geometry":{"type":"Point","coordinates":[-114.66325,35.82014]},"properties":{"id":4,"numid":4,"stationid":4,"name":"Malpais Flattop Mesa (NPS)","in_service":1,"interval_data":"0.35","interval_time":43200,"novascore":1}},{"type":"Feature","geometry":{"type":"Point","coordinates":[-115.641639,36.573]},"properties":{"id":1089,"numid":3634,"stationid":3634,"name":"Indian Springs 1","description":"Weather Station","in_service":1,"interval_data":"0.16","interval_time":43200,"novascore":1}},{"type":"Feature","geometry":{"type":"Point","coordinates":[-114.714083,36.773889]},"properties":{"id":1254,"numid":3239,"stationid":3239,"name":"Dry Gulch","description":"Rain Gauge A2","in_service":1,"interval_data":"0.16","interval_time":43200,"novascore":1}},{"type":"Feature","geometry":{"type":"Point","coordinates":[-115.600778,36.507667]},"properties":{"id":1248,"numid":3644,"stationid":3644,"name":"Indian Springs 2","description":"Weather Station","in_service":1,"interval_data":"0.16","interval_time":43200,"novascore":1}},{"type":"Feature","geometry":{"type":"Point","coordinates":[-115.254028,36.065917]},"properties":{"id":374,"numid":4434,"stationid":4434,"name":"Beltway Channel at Buffalo","description":"Water Level Float","in_service":1,"interval_data":"0.28","interval_time":43200,"novascore":1}},{"type":"Feature","geometry":{"type":"Point","coordinates":[-115.109569,36.034639]},"properties":{"id":463,"numid":4734,"stationid":4734,"name":"Pittman Wash at Wigwam","description":"Water Level Float","in_service":1,"interval_data":"0.39","interval_time":43200,"novascore":1}},{"type":"Feature","geometry":{"type":"Point","coordinates":[-115.249167,36.276389]},"properties":{"id":970,"numid":4559,"stationid":4559,"name":"Beltway Channel at Tenaya","description":"Water Level Float","in_service":1,"interval_data":"0.63","interval_time":43200,"novascore":1}},{"type":"Feature","geometry":{"type":"Point","coordinates":[-115.048989,36.139789]},"properties":{"id":1024,"numid":4599,"stationid":4599,"name":"Las Vegas Wash at The Club at Sunrise (USGS)","description":"Radar WL site. The Club was formerly named Desert Rose Golf Course. Located at the confluence of the Las Vegas and Flamingo Washes.","in_service":1,"interval_data":"0.24","interval_time":43200,"novascore":1}},{"type":"Feature","geometry":{"type":"Point","coordinates":[-115.211944,36.325472]},"properties":{"id":178,"numid":4024,"stationid":4024,"name":"Upper Las Vegas Wash DB","description":"Water Level Bubbler","in_service":1,"interval_data":"0.31","interval_time":43200,"novascore":1}},{"type":"Feature","geometry":{"type":"Point","coordinates":[-115.212222,36.046667]},"properties":{"id":383,"numid":4459,"stationid":4459,"name":"Lower Blue Diamond DB","description":"Water Level Bubbler","in_service":1,"interval_data":"0.31","interval_time":43200,"novascore":1}},{"type":"Feature","geometry":{"type":"Point","coordinates":[-114.95875,36.021861]},"properties":{"id":484,"numid":4779,"stationid":4779,"name":"C-1 Channel near Boulder Hwy","description":"Water Level Float","in_service":1,"interval_data":"0.28","interval_time":43200,"novascore":1}},{"type":"Feature","geometry":{"type":"Point","coordinates":[-115.333611,36.251556]},"properties":{"id":188,"numid":4054,"stationid":4054,"name":"Lone Mtn at Hualapai","description":"Rain Gauge","in_service":1,"interval_data":"0.98","interval_time":43200,"novascore":1}},{"type":"Feature","geometry":{"type":"Point","coordinates":[-114.985833,36.087083]},"properties":{"id":410,"numid":4544,"stationid":4544,"name":"Las Vegas Wash at Pabco Rd","description":"Water Level Float","in_service":1,"interval_data":"0.00","interval_time":43200,"novascore":1}},{"type":"Feature","geometry":{"type":"Point","coordinates":[-115.103194,36.133167]},"properties":{"id":359,"numid":4399,"stationid":4399,"name":"Flamingo Wash at Mojave","description":"Water Level Float","in_service":1,"interval_data":"0.35","interval_time":43200,"novascore":1}},{"type":"Feature","geometry":{"type":"Point","coordinates":[-114.891556,35.701278]},"properties":{"id":492,"numid":4814,"stationid":4814,"name":"Nelson","description":"Weather Station","in_service":1,"interval_data":"0.08","interval_time":43200,"novascore":1}},{"type":"Feature","geometry":{"type":"Point","coordinates":[-115.223333,36.057028]},"properties":{"id":381,"numid":4454,"stationid":4454,"name":"Warm Springs at Jones","description":"Weather Station","in_service":1,"interval_data":"0.35","interval_time":43200,"novascore":1}},{"type":"Feature","geometry":{"type":"Point","coordinates":[-115.188028,35.72925]},"properties":{"id":531,"numid":4984,"stationid":4984,"name":"Jean SE2","description":"Weather Station","in_service":1,"interval_data":"0.28","interval_time":43200,"novascore":1}},{"type":"Feature","geometry":{"type":"Point","coordinates":[-115.159806,36.243139]},"properties":{"id":190,"numid":4059,"stationid":4059,"name":"Gowan Outfall Channel","description":"Water Level Bubbler","in_service":1,"interval_data":"0.43","interval_time":43200,"novascore":1}},{"type":"Feature","geometry":{"type":"Point","coordinates":[-115.16,36.255]},"properties":{"id":192,"numid":4064,"stationid":4064,"name":"Lower Las Vegas Wash DB","description":"Water Level Bubbler","in_service":1,"interval_data":"0.39","interval_time":43200,"novascore":1}},{"type":"Feature","geometry":{"type":"Point","coordinates":[-115.044542,36.159564]},"properties":{"id":226,"numid":4174,"stationid":4174,"name":"Sloan Channel at Charleston (USGS)","in_service":1,"interval_data":"0.12","interval_time":43200,"novascore":1}},{"type":"Feature","geometry":{"type":"Point","coordinates":[-115.354658,36.152586]},"properties":{"id":295,"numid":4344,"stationid":4344,"name":"Red Rock DB","description":"Water Level Bubbler","in_service":1,"interval_data":"0.75","interval_time":43200,"novascore":1}},{"type":"Feature","geometry":{"type":"Point","coordinates":[-115.12925,35.9685]},"properties":{"id":457,"numid":4719,"stationid":4719,"name":"Pittman East DB","description":"Water Level Bubbler","in_service":1,"interval_data":"0.20","interval_time":43200,"novascore":1}},{"type":"Feature","geometry":{"type":"Point","coordinates":[-115.079139,36.335]},"properties":{"id":217,"numid":4134,"stationid":4134,"name":"West Range Wash 2","description":"Rain Gauge","in_service":1,"interval_data":"0.52","interval_time":43200,"novascore":1}},{"type":"Feature","geometry":{"type":"Point","coordinates":[-115.324222,36.119889]},"properties":{"id":287,"numid":4319,"stationid":4319,"name":"Beltway Channel at Town Center","description":"Water Level Float","in_service":1,"interval_data":"0.51","interval_time":43200,"novascore":1}},{"type":"Feature","geometry":{"type":"Point","coordinates":[-115.111364,36.108356]},"properties":{"id":311,"numid":4379,"stationid":4379,"name":"Van Buskirk DB","description":"Water Level Float","in_service":1,"interval_data":"0.43","interval_time":43200,"novascore":1}},{"type":"Feature","geometry":{"type":"Point","coordinates":[-115.338861,36.097194]},"properties":{"id":361,"numid":4404,"stationid":4404,"name":"F-1 Debris Basin","description":"Water Level Bubbler","in_service":1,"interval_data":"0.56","interval_time":43200,"novascore":1}},{"type":"Feature","geometry":{"type":"Point","coordinates":[-115.292417,36.161028]},"properties":{"id":250,"numid":4229,"stationid":4229,"name":"Charleston at Rampart","description":"Rain Gauge","in_service":1,"interval_data":"0.47","interval_time":43200,"novascore":1}},{"type":"Feature","geometry":{"type":"Point","coordinates":[-115.244444,36.154722]},"properties":{"id":254,"numid":4244,"stationid":4244,"name":"Oakey at Rainbow","description":"Weather Station","in_service":1,"interval_data":"0.39","interval_time":43200,"novascore":1}},{"type":"Feature","geometry":{"type":"Point","coordinates":[-115.261333,36.202528]},"properties":{"id":251,"numid":4234,"stationid":4234,"name":"Smoke Ranch at Buffalo","description":"Rain Gauge","in_service":1,"interval_data":"0.51","interval_time":43200,"novascore":1}},{"type":"Feature","geometry":{"type":"Point","coordinates":[-115.296778,36.107028]},"properties":{"id":292,"numid":4339,"stationid":4339,"name":"Beltway Channel at Peace Way","description":"Water Level Float","in_service":1,"interval_data":"0.47","interval_time":43200,"novascore":1}},{"type":"Feature","geometry":{"type":"Point","coordinates":[-114.860278,35.980556]},"properties":{"id":503,"numid":4844,"stationid":4844,"name":"Bootleg Canyon DB","description":"Water Level Float","in_service":1,"interval_data":"0.39","interval_time":43200,"novascore":1}},{"type":"Feature","geometry":{"type":"Point","coordinates":[-114.864222,35.995556]},"properties":{"id":505,"numid":4854,"stationid":4854,"name":"Boulder City","description":"Weather Station","in_service":1,"interval_data":"0.20","interval_time":43200,"novascore":1}},{"type":"Feature","geometry":{"type":"Point","coordinates":[-115.38575,36.083764]},"properties":{"id":280,"numid":4304,"stationid":4304,"name":"Blue Diamond Ridge South","description":"Weather Station","in_service":1,"interval_data":"0.63","interval_time":43200,"novascore":1}},{"type":"Feature","geometry":{"type":"Point","coordinates":[-114.309083,36.867056]},"properties":{"id":106,"numid":3034,"stationid":3034,"name":"Halfway Wash","description":"Rain Gauge","in_service":1,"interval_data":"0.35","interval_time":43200,"novascore":1}},{"type":"Feature","geometry":{"type":"Point","coordinates":[-114.114444,36.8175]},"properties":{"id":84,"numid":2674,"stationid":2674,"name":"Pulsipher Wash DB","description":"Water Level Float","in_service":1,"interval_data":"0.24","interval_time":43200,"novascore":1}},{"type":"Feature","geometry":{"type":"Point","coordinates":[-114.418056,36.664722]},"properties":{"id":123,"numid":3244,"stationid":3244,"name":"Mormon Mesa 2","description":"Weather Station","in_service":1,"interval_data":"0.20","interval_time":43200,"novascore":1}},{"type":"Feature","geometry":{"type":"Point","coordinates":[-114.036056,36.951944]},"properties":{"id":72,"numid":2564,"stationid":2564,"name":"Mesquite 1","description":"Rain Gauge","in_service":1,"interval_data":"0.31","interval_time":43200,"novascore":1}},{"type":"Feature","geometry":{"type":"Point","coordinates":[-114.085611,36.8065]},"properties":{"id":88,"numid":2694,"stationid":2694,"name":"Abbott Wash Channel","description":"Water Level Float","in_service":1,"interval_data":"0.24","interval_time":43200,"novascore":1}},{"type":"Feature","geometry":{"type":"Point","coordinates":[-114.706833,36.479806]},"properties":{"id":110,"numid":3144,"stationid":3144,"name":"California Wash 3","description":"Weather Station.  A.K.A. Paiute Point.","in_service":1,"interval_data":"0.16","interval_time":43200,"novascore":1}},{"type":"Feature","geometry":{"type":"Point","coordinates":[-114.502861,36.456556]},"properties":{"id":135,"numid":3284,"stationid":3284,"name":"Silica Dome","description":"Weather Station","in_service":1,"interval_data":"0.16","interval_time":43200,"novascore":1}},{"type":"Feature","geometry":{"type":"Point","coordinates":[-114.636778,36.542639]},"properties":{"id":113,"numid":3164,"stationid":3164,"name":"California Wash 1","description":"Rain Gauge","in_service":1,"interval_data":"0.20","interval_time":43200,"novascore":1}},{"type":"Feature","geometry":{"type":"Point","coordinates":[-115.074286,36.228717]},"properties":{"id":213,"numid":4114,"stationid":4114,"name":"Sloan Channel at Las Vegas Blvd","in_service":1,"interval_data":"0.31","interval_time":43200,"novascore":1}},{"type":"Feature","geometry":{"type":"Point","coordinates":[-114.631389,36.631194]},"properties":{"id":115,"numid":3184,"stationid":3184,"name":"California Wash 2","description":"Water Level Float","in_service":1,"interval_data":"0.28","interval_time":43200,"novascore":1}},{"type":"Feature","geometry":{"type":"Point","coordinates":[-115.105417,36.210306]},"properties":{"id":403,"numid":4529,"stationid":4529,"name":"Las Vegas Wash at LV Blvd","description":"Water Level Bubbler","in_service":1,"interval_data":"0.40","interval_time":43200,"novascore":1}},{"type":"Feature","geometry":{"type":"Point","coordinates":[-115.234144,36.102719]},"properties":{"id":305,"numid":4364,"stationid":4364,"name":"Flamingo Wash at Torrey Pines Dr.","description":"Water Level Float","in_service":1,"interval_data":"0.39","interval_time":43200,"novascore":1}},{"type":"Feature","geometry":{"type":"Point","coordinates":[-115.257639,36.321556]},"properties":{"id":170,"numid":4009,"stationid":4009,"name":"Floyd Lamb North EEA","description":"Water Level Bubbler","in_service":1,"interval_data":"0.67","interval_time":43200,"novascore":1}},{"type":"Feature","geometry":{"type":"Point","coordinates":[-115.267139,36.319083]},"properties":{"id":176,"numid":4019,"stationid":4019,"name":"Floyd Lamb South EEA","description":"Water Level Bubbler","in_service":1,"interval_data":"0.52","interval_time":43200,"novascore":1}},{"type":"Feature","geometry":{"type":"Point","coordinates":[-115.275333,36.232722]},"properties":{"id":270,"numid":4279,"stationid":4279,"name":"Gowan North Channel","description":"Water Level Float","in_service":1,"interval_data":"0.75","interval_time":43200,"novascore":1}},{"type":"Feature","geometry":{"type":"Point","coordinates":[-115.030167,36.325694]},"properties":{"id":216,"numid":4124,"stationid":4124,"name":"West Range Wash 1","description":"Rain Gauge","in_service":1,"interval_data":"0.00","interval_time":43200,"novascore":1}},{"type":"Feature","geometry":{"type":"Point","coordinates":[-115.397828,36.107511]},"properties":{"id":285,"numid":4314,"stationid":4314,"name":"Blue Diamond Ridge North","description":"Rain Gauge","in_service":1,"interval_data":"0.55","interval_time":43200,"novascore":1}},{"type":"Feature","geometry":{"type":"Point","coordinates":[-115.241492,36.357225]},"properties":{"id":186,"numid":4044,"stationid":4044,"name":"Castle Rock","description":"Rain Gauge","in_service":1,"interval_data":"0.47","interval_time":43200,"novascore":1}},{"type":"Feature","geometry":{"type":"Point","coordinates":[-114.389194,36.561694]},"properties":{"id":133,"numid":3279,"stationid":3279,"name":"Mormon Mesa Overton","description":"Rain Gauge","in_service":1,"interval_data":"0.12","interval_time":43200,"novascore":1}},{"type":"Feature","geometry":{"type":"Point","coordinates":[-114.438056,36.565]},"properties":{"id":139,"numid":3294,"stationid":3294,"name":"Overton Airport","description":"Weather Station","in_service":1,"interval_data":"0.12","interval_time":43200,"novascore":1}},{"type":"Feature","geometry":{"type":"Point","coordinates":[-114.055444,36.837028]},"properties":{"id":75,"numid":2584,"stationid":2584,"name":"Mesquite Airport","description":"Weather Station","in_service":1,"interval_data":"0.16","interval_time":43200,"novascore":1}},{"type":"Feature","geometry":{"type":"Point","coordinates":[-114.200528,36.9335]},"properties":{"id":82,"numid":2664,"stationid":2664,"name":"Mesquite 2","description":"Rain Gauge","in_service":1,"interval_data":"0.47","interval_time":43200,"novascore":1}},{"type":"Feature","geometry":{"type":"Point","coordinates":[-114.532833,36.595083]},"properties":{"id":132,"numid":3274,"stationid":3274,"name":"Logan Wash","description":"Rain Gauge","in_service":1,"interval_data":"0.24","interval_time":43200,"novascore":1}},{"type":"Feature","geometry":{"type":"Point","coordinates":[-115.042889,36.211167]},"properties":{"id":224,"numid":4154,"stationid":4154,"name":"Confluence DB","description":"Water Level Float","in_service":1,"interval_data":"0.31","interval_time":43200,"novascore":1}},{"type":"Feature","geometry":{"type":"Point","coordinates":[-115.145403,36.165733]},"properties":{"id":266,"numid":4274,"stationid":4274,"name":"Downtown Las Vegas","description":"Weather Station","in_service":1,"interval_data":"0.39","interval_time":43200,"novascore":1}},{"type":"Feature","geometry":{"type":"Point","coordinates":[-115.682556,36.571139]},"properties":{"id":147,"numid":3619,"stationid":3619,"name":"Indian Springs DB","description":"Water Level Float","in_service":1,"interval_data":"0.16","interval_time":43200,"novascore":1}},{"type":"Feature","geometry":{"type":"Point","coordinates":[-115.281417,36.187]},"properties":{"id":245,"numid":4219,"stationid":4219,"name":"Angel Park DB","description":"Water Level Bubbler","in_service":1,"interval_data":"0.51","interval_time":43200,"novascore":1}},{"type":"Feature","geometry":{"type":"Point","coordinates":[-115.065856,36.142378]},"properties":{"id":357,"numid":4394,"stationid":4394,"name":"Flamingo Wash at Nellis Blvd (USGS)","in_service":1,"interval_data":"0.39","interval_time":43200,"novascore":1}},{"type":"Feature","geometry":{"type":"Point","coordinates":[-115.183667,36.172917]},"properties":{"id":276,"numid":4294,"stationid":4294,"name":"Meadows DB","description":"Water Level Bubbler","in_service":1,"interval_data":"0.47","interval_time":43200,"novascore":1}},{"type":"Feature","geometry":{"type":"Point","coordinates":[-115.234833,36.151092]},"properties":{"id":256,"numid":4249,"stationid":4249,"name":"Oakey DB","description":"Water Level Float","in_service":1,"interval_data":"0.28","interval_time":43200,"novascore":1}},{"type":"Feature","geometry":{"type":"Point","coordinates":[-115.046389,36.075833]},"properties":{"id":469,"numid":4749,"stationid":4749,"name":"Pittman Wash at Stephanie","description":"Water Level Bubbler","in_service":1,"interval_data":"0.27","interval_time":43200,"novascore":1}},{"type":"Feature","geometry":{"type":"Point","coordinates":[-115.2425,36.173889]},"properties":{"id":278,"numid":4299,"stationid":4299,"name":"Rainbow Curve DB","description":"Water Level Bubbler","in_service":1,"interval_data":"0.39","interval_time":43200,"novascore":1}},{"type":"Feature","geometry":{"type":"Point","coordinates":[-114.547833,36.7495]},"properties":{"id":108,"numid":3064,"stationid":3064,"name":"Weiser Wash","description":"Rain Gauge (Can serve as a backup repeater for Moapa region)","in_service":1,"interval_data":"0.12","interval_time":43200,"novascore":1}},{"type":"Feature","geometry":{"type":"Point","coordinates":[-115.194228,35.927561]},"properties":{"id":448,"numid":4704,"stationid":4704,"name":"Sloan at I-15","description":"Weather Station","in_service":1,"interval_data":"0.28","interval_time":43200,"novascore":1}},{"type":"Feature","geometry":{"type":"Point","coordinates":[-115.285444,36.124444]},"properties":{"id":299,"numid":4354,"stationid":4354,"name":"The Lakes","description":"Weather Station","in_service":1,"interval_data":"0.39","interval_time":43200,"novascore":1}},{"type":"Feature","geometry":{"type":"Point","coordinates":[-115.087944,36.252639]},"properties":{"id":215,"numid":4119,"stationid":4119,"name":"Vandenberg DB","description":"Water Level Float","in_service":1,"interval_data":"0.31","interval_time":43200,"novascore":1}},{"type":"Feature","geometry":{"type":"Point","coordinates":[-115.309447,36.232267]},"properties":{"id":264,"numid":4269,"stationid":4269,"name":"Lone Mountain DB","description":"Water Level Float","in_service":1,"interval_data":"0.87","interval_time":43200,"novascore":1}},{"type":"Feature","geometry":{"type":"Point","coordinates":[-115.112333,36.242583]},"properties":{"id":194,"numid":4069,"stationid":4069,"name":"Las Vegas Wash at Craig Rd","description":"Water Level Float","in_service":1,"interval_data":"0.35","interval_time":43200,"novascore":1}},{"type":"Feature","geometry":{"type":"Point","coordinates":[-115.024322,36.224481]},"properties":{"id":211,"numid":4109,"stationid":4109,"name":"Nellis AFB South","description":"Rain Gauge","in_service":1,"interval_data":"0.24","interval_time":43200,"novascore":1}},{"type":"Feature","geometry":{"type":"Point","coordinates":[-114.943028,36.1]},"properties":{"id":206,"numid":4099,"stationid":4099,"name":"Rainbow Garden Weir","description":"Water Level Float","in_service":1,"interval_data":"0.16","interval_time":43200,"novascore":1}},{"type":"Feature","geometry":{"type":"Point","coordinates":[-115.480778,36.283]},"properties":{"id":154,"numid":3914,"stationid":3914,"name":"Grapevine Springs 2","description":"Weather Station","in_service":1,"interval_data":"0.91","interval_time":43200,"novascore":1}},{"type":"Feature","geometry":{"type":"Point","coordinates":[-115.370417,36.369917]},"properties":{"id":166,"numid":3954,"stationid":3954,"name":"Tule Springs NW","description":"Weather Station","in_service":1,"interval_data":"0.43","interval_time":43200,"novascore":1}},{"type":"Feature","geometry":{"type":"Point","coordinates":[-115.208583,36.102583]},"properties":{"id":307,"numid":4369,"stationid":4369,"name":"Lower Flamingo DB","description":"Water Level Bubbler","in_service":1,"interval_data":"0.43","interval_time":43200,"novascore":1}},{"type":"Feature","geometry":{"type":"Point","coordinates":[-114.918333,36.336667]},"properties":{"id":220,"numid":4144,"stationid":4144,"name":"Apex","description":"Weather Station","in_service":1,"interval_data":"0.51","interval_time":43200,"novascore":1}},{"type":"Feature","geometry":{"type":"Point","coordinates":[-115.269222,36.317833]},"properties":{"id":187,"numid":4049,"stationid":4049,"name":"Floyd Lamb City Park","description":"Rain Gauge","in_service":1,"interval_data":"0.71","interval_time":43200,"novascore":1}},{"type":"Feature","geometry":{"type":"Point","coordinates":[-115.180694,36.198111]},"properties":{"id":253,"numid":4239,"stationid":4239,"name":"Carey/Lake Mead DB","description":"Water Level Bubbler","in_service":1,"interval_data":"0.35","interval_time":43200,"novascore":1}},{"type":"Feature","geometry":{"type":"Point","coordinates":[-115.136583,36.356417]},"properties":{"id":185,"numid":4039,"stationid":4039,"name":"North Valley 2","description":"Rain Gauge","in_service":1,"interval_data":"0.67","interval_time":43200,"novascore":1}},{"type":"Feature","geometry":{"type":"Point","coordinates":[-115.270611,36.090111]},"properties":{"id":297,"numid":4349,"stationid":4349,"name":"Upper Flamingo DB","description":"Water Level Bubbler","in_service":1,"interval_data":"0.31","interval_time":43200,"novascore":1}},{"type":"Feature","geometry":{"type":"Point","coordinates":[-114.932556,36.033194]},"properties":{"id":488,"numid":4794,"stationid":4794,"name":"East Henderson 1","description":"Rain Gauge","in_service":1,"interval_data":"0.24","interval_time":43200,"novascore":1}},{"type":"Feature","geometry":{"type":"Point","coordinates":[-115.305306,36.087139]},"properties":{"id":370,"numid":4424,"stationid":4424,"name":"F-1 Channel","description":"Water Level Float","in_service":1,"interval_data":"0.39","interval_time":43200,"novascore":1}},{"type":"Feature","geometry":{"type":"Point","coordinates":[-115.297444,36.281028]},"properties":{"id":395,"numid":4509,"stationid":4509,"name":"Fort Apache DB","description":"Water Level Bubbler / DA  H-350XL","in_service":1,"interval_data":"0.75","interval_time":43200,"novascore":1}},{"type":"Feature","geometry":{"type":"Point","coordinates":[-115.466028,35.809917]},"properties":{"id":510,"numid":4924,"stationid":4924,"name":"Goodsprings 1","description":"Weather Station","in_service":1,"interval_data":"0.47","interval_time":43200,"novascore":1}},{"type":"Feature","geometry":{"type":"Point","coordinates":[-115.127778,35.943056]},"properties":{"id":467,"numid":4744,"stationid":4744,"name":"Headworks Channel","description":"Water Level Float","in_service":1,"interval_data":"0.31","interval_time":43200,"novascore":1}},{"type":"Feature","geometry":{"type":"Point","coordinates":[-115.117,35.925]},"properties":{"id":452,"numid":4709,"stationid":4709,"name":"Headworks DB","description":"Water Level Bubbler","in_service":1,"interval_data":"0.28","interval_time":43200,"novascore":1}},{"type":"Feature","geometry":{"type":"Point","coordinates":[-115.357861,36.182611]},"properties":{"id":236,"numid":4204,"stationid":4204,"name":"Summerlin West","description":"Weather Station","in_service":1,"interval_data":"0.98","interval_time":43200,"novascore":1}},{"type":"Feature","geometry":{"type":"Point","coordinates":[-115.042833,36.143194]},"properties":{"id":233,"numid":4199,"stationid":4199,"name":"Sloan Channel below Sahara","description":"Water Level Float","in_service":1,"interval_data":"0.35","interval_time":43200,"novascore":1}},{"type":"Feature","geometry":{"type":"Point","coordinates":[-114.005833,36.808056]},"properties":{"id":568,"numid":7750,"stationid":7750,"name":"Virgin River at Scenic, AZ (Mohave County)","in_service":1,"interval_data":"0.16","interval_time":43200,"novascore":1}},{"type":"Feature","geometry":{"type":"Point","coordinates":[-115.281389,36.035]},"properties":{"id":376,"numid":4439,"stationid":4439,"name":"Blue Diamond Channel","description":"Water Level Float","in_service":1,"interval_data":"0.24","interval_time":43200,"novascore":1}},{"type":"Feature","geometry":{"type":"Point","coordinates":[-114.955361,35.988139]},"properties":{"id":475,"numid":4764,"stationid":4764,"name":"Mission Hills DB","description":"Water Level Float","in_service":1,"interval_data":"0.12","interval_time":43200,"novascore":1}},{"type":"Feature","geometry":{"type":"Point","coordinates":[-115.138917,36.045222]},"properties":{"id":424,"numid":4624,"stationid":4624,"name":"Duck Creek at Paradise","description":"Water Level Float","in_service":1,"interval_data":"0.43","interval_time":43200,"novascore":1}},{"type":"Feature","geometry":{"type":"Point","coordinates":[-115.199444,36.081444]},"properties":{"id":386,"numid":4474,"stationid":4474,"name":"Tropicana DB","description":"Water Level Bubbler","in_service":1,"interval_data":"0.39","interval_time":43200,"novascore":1}},{"type":"Feature","geometry":{"type":"Point","coordinates":[-115.155222,36.021111]},"properties":{"id":422,"numid":4619,"stationid":4619,"name":"Lower Duck Creek DB","description":"Water Level Bubbler","in_service":1,"interval_data":"0.28","interval_time":43200,"novascore":1}},{"type":"Feature","geometry":{"type":"Point","coordinates":[-115.185028,36.286722]},"properties":{"id":407,"numid":4539,"stationid":4539,"name":"Beltway Channel at Aliante","description":"Water Level Float","in_service":1,"interval_data":"0.51","interval_time":43200,"novascore":1}},{"type":"Feature","geometry":{"type":"Point","coordinates":[-115.204167,36.572778]},"properties":{"id":157,"numid":3924,"stationid":3924,"name":"Yucca Forest 1","description":"Rain Gauge","in_service":1,"interval_data":"0.00","interval_time":43200,"novascore":1}},{"type":"Feature","geometry":{"type":"Point","coordinates":[-115.164472,36.130694]},"properties":{"id":313,"numid":4384,"stationid":4384,"name":"DI Super Arterial","in_service":1,"interval_data":"0.47","interval_time":43200,"novascore":1}},{"type":"Feature","geometry":{"type":"Point","coordinates":[-115.326083,36.225833]},"properties":{"id":392,"numid":4504,"stationid":4504,"name":"Beltway Channel at Cheyenne","description":"Water Level Float","in_service":1,"interval_data":"0.94","interval_time":43200,"novascore":1}},{"type":"Feature","geometry":{"type":"Point","coordinates":[-114.1225,36.766111]},"properties":{"id":94,"numid":2784,"stationid":2784,"name":"Windmill Wash DB","description":"Water Level Bubbler","in_service":1,"interval_data":"0.04","interval_time":43200,"novascore":1}},{"type":"Feature","geometry":{"type":"Point","coordinates":[-115.328778,36.079917]},"properties":{"id":363,"numid":4409,"stationid":4409,"name":"F-2 Debris Basin","description":"Water Level Bubbler","in_service":1,"interval_data":"0.39","interval_time":43200,"novascore":1}},{"type":"Feature","geometry":{"type":"Point","coordinates":[-114.921333,36.013028]},"properties":{"id":487,"numid":4789,"stationid":4789,"name":"East Henderson 2","description":"Rain Gauge","in_service":1,"interval_data":"0.20","interval_time":43200,"novascore":1}},{"type":"Feature","geometry":{"type":"Point","coordinates":[-115.316694,36.031861]},"properties":{"id":365,"numid":4414,"stationid":4414,"name":"Blue Diamond DB","description":"Water Level Bubbler","in_service":1,"interval_data":"0.28","interval_time":43200,"novascore":1}},{"type":"Feature","geometry":{"type":"Point","coordinates":[-115.309028,35.673833]},"properties":{"id":526,"numid":4974,"stationid":4974,"name":"Jean SE3","description":"Weather Station","in_service":1,"interval_data":"0.31","interval_time":43200,"novascore":1}},{"type":"Feature","geometry":{"type":"Point","coordinates":[-114.715861,35.132861]},"properties":{"id":551,"numid":5234,"stationid":5234,"name":"Laughlin 3","description":"Rain Gauge","in_service":1,"interval_data":"0.28","interval_time":43200,"novascore":1}},{"type":"Feature","geometry":{"type":"Point","coordinates":[-115.092583,35.983861]},"properties":{"id":461,"numid":4729,"stationid":4729,"name":"McCullough Hills DB","description":"Water Level Bubbler","in_service":1,"interval_data":"0.31","interval_time":43200,"novascore":1}},{"type":"Feature","geometry":{"type":"Point","coordinates":[-115.331667,36.1205]},"properties":{"id":380,"numid":4449,"stationid":4449,"name":"R-4 Channel","description":"Water Level Float","in_service":1,"interval_data":"0.55","interval_time":43200,"novascore":1}},{"type":"Feature","geometry":{"type":"Point","coordinates":[-115.353583,36.112722]},"properties":{"id":378,"numid":4444,"stationid":4444,"name":"R-4 DB","description":"Water Level Float","in_service":1,"interval_data":"0.59","interval_time":43200,"novascore":1}},{"type":"Feature","geometry":{"type":"Point","coordinates":[-115.261111,36.268056]},"properties":{"id":399,"numid":4519,"stationid":4519,"name":"Rancho DB","description":"Water Level Bubbler","in_service":1,"interval_data":"0.70","interval_time":43200,"novascore":1}},{"type":"Feature","geometry":{"type":"Point","coordinates":[-115.315353,36.009675]},"properties":{"id":430,"numid":4639,"stationid":4639,"name":"Upper Duck Creek DB","description":"Water Level Bubbler","in_service":1,"interval_data":"0.24","interval_time":43200,"novascore":1}},{"type":"Feature","geometry":{"type":"Point","coordinates":[-115.11914,36.2583]},"properties":{"id":405,"numid":4534,"stationid":4534,"name":"Upper Las Vegas Wash 1","description":"Water Level Float","in_service":1,"interval_data":"0.35","interval_time":43200,"novascore":1}},{"type":"Feature","geometry":{"type":"Point","coordinates":[-115.299722,36.044722]},"properties":{"id":368,"numid":4419,"stationid":4419,"name":"F-4 Debris Basin","description":"Water Level Float","in_service":1,"interval_data":"0.24","interval_time":43200,"novascore":1}},{"type":"Feature","geometry":{"type":"Point","coordinates":[-114.936667,36.055556]},"properties":{"id":412,"numid":4549,"stationid":4549,"name":"NE C-1 DB","description":"Water Level Bubbler","in_service":1,"interval_data":"0.23","interval_time":43200,"novascore":1}},{"type":"Feature","geometry":{"type":"Point","coordinates":[-115.169444,36.009722]},"properties":{"id":426,"numid":4629,"stationid":4629,"name":"Duck Creek at JoRae","description":"Water Level Float","in_service":1,"interval_data":"0.28","interval_time":43200,"novascore":1}},{"type":"Feature","geometry":{"type":"Point","coordinates":[-115.251528,35.975194]},"properties":{"id":438,"numid":4654,"stationid":4654,"name":"Tortoise Center","description":"Weather Station","in_service":1,"interval_data":"0.23","interval_time":43200,"novascore":1}},{"type":"Feature","geometry":{"type":"Point","coordinates":[-114.632628,35.155425]},"properties":{"id":557,"numid":5274,"stationid":5274,"name":"Hiko Springs DB","description":"Water Level Bubbler","in_service":1,"interval_data":"0.24","interval_time":43200,"novascore":1}},{"type":"Feature","geometry":{"type":"Point","coordinates":[-114.281,35.225]},"properties":{"id":876,"numid":1520,"stationid":1520,"name":"Upper Sacramento Wash (Mohave County)","in_service":1,"interval_data":"0.24","interval_time":43200,"novascore":1}},{"type":"Feature","geometry":{"type":"Point","coordinates":[-115.285556,35.997778]},"properties":{"id":419,"numid":4609,"stationid":4609,"name":"Cactus near Durango","description":"Rain Gauge","in_service":1,"interval_data":"0.31","interval_time":43200,"novascore":1}},{"type":"Feature","geometry":{"type":"Point","coordinates":[-115.398639,35.738389]},"properties":{"id":516,"numid":4944,"stationid":4944,"name":"Jean Southwest","description":"Weather Station","in_service":1,"interval_data":"0.55","interval_time":43200,"novascore":1}},{"type":"Feature","geometry":{"type":"Point","coordinates":[-115.166667,36.343167]},"properties":{"id":182,"numid":4034,"stationid":4034,"name":"North Valley 1","description":"Weather Station","in_service":1,"interval_data":"0.08","interval_time":43200,"novascore":1}},{"type":"Feature","geometry":{"type":"Point","coordinates":[-115.184528,36.046861]},"properties":{"id":432,"numid":4644,"stationid":4644,"name":"NWS Offices","description":"Weather Station","in_service":1,"interval_data":"0.35","interval_time":43200,"novascore":1}},{"type":"Feature","geometry":{"type":"Point","coordinates":[-114.399,35.004]},"properties":{"id":877,"numid":1590,"stationid":1590,"name":"Boundary Cone (Mohave County)","in_service":1,"interval_data":"0.43","interval_time":43200,"novascore":1}},{"type":"Feature","geometry":{"type":"Point","coordinates":[-113.968,36.8653]},"properties":{"id":854,"numid":1615,"stationid":1615,"name":"Big Bend Wash @ I-15 (Mohave County)","in_service":1,"interval_data":"0.20","interval_time":43200,"novascore":1}},{"type":"Feature","geometry":{"type":"Point","coordinates":[-115.338333,36.300389]},"properties":{"id":180,"numid":4029,"stationid":4029,"name":"Kyle Canyon DB","description":"Water Level Bubbler","in_service":1,"interval_data":"0.55","interval_time":43200,"novascore":1}},{"type":"Feature","geometry":{"type":"Point","coordinates":[-115.278417,36.127833]},"properties":{"id":303,"numid":4359,"stationid":4359,"name":"The Lakes DB","description":"Water Level Float","in_service":1,"interval_data":"0.35","interval_time":43200,"novascore":1}},{"type":"Feature","geometry":{"type":"Point","coordinates":[-115.216167,35.665861]},"properties":{"id":523,"numid":4964,"stationid":4964,"name":"Jean SE","description":"Rain Gauge","in_service":1,"interval_data":"0.63","interval_time":43200,"novascore":1}},{"type":"Feature","geometry":{"type":"Point","coordinates":[-115.340028,36.2695]},"properties":{"id":397,"numid":4514,"stationid":4514,"name":"CAM-10 DB","description":"Water Level Bubbler","in_service":1,"interval_data":"0.20","interval_time":43200,"novascore":1}},{"type":"Feature","geometry":{"type":"Point","coordinates":[-115.447306,35.850389]},"properties":{"id":508,"numid":4914,"stationid":4914,"name":"Goodsprings 2","description":"Rain Gauge","in_service":1,"interval_data":"1.10","interval_time":43200,"novascore":1}},{"type":"Feature","geometry":{"type":"Point","coordinates":[-115.128917,36.119583]},"properties":{"id":418,"numid":4574,"stationid":4574,"name":"Flamingo Wash at Spencer","description":"Water Level Float","in_service":1,"interval_data":"0.39","interval_time":43200,"novascore":1}},{"type":"Feature","geometry":{"type":"Point","coordinates":[-115.285611,36.430806]},"properties":{"id":172,"numid":4014,"stationid":4014,"name":"Fossil Ridge","description":"Weather Station","in_service":1,"interval_data":"0.24","interval_time":43200,"novascore":1}},{"type":"Feature","geometry":{"type":"Point","coordinates":[-114.708,35.49]},"properties":{"id":49,"numid":400,"stationid":400,"name":"Cottonwood Cove East (NPS)","in_service":1,"interval_data":"0.12","interval_time":43200,"novascore":1}},{"type":"Feature","geometry":{"type":"Point","coordinates":[-115.686194,36.445611]},"properties":{"id":149,"numid":3704,"stationid":3704,"name":"Cold Creek 1","description":"Weather Station","in_service":1,"interval_data":"0.00","interval_time":43200,"novascore":1}},{"type":"Feature","geometry":{"type":"Point","coordinates":[-115.309167,36.171778]},"properties":{"id":247,"numid":4224,"stationid":4224,"name":"Angel Park West","description":"Weather Station","in_service":1,"interval_data":"0.58","interval_time":43200,"novascore":1}},{"type":"Feature","geometry":{"type":"Point","coordinates":[-114.580278,34.87]},"properties":{"id":858,"numid":1655,"stationid":1655,"name":"Quail Run (Mohave County)","in_service":1,"interval_data":"M","interval_time":43200,"novascore":1}},{"type":"Feature","geometry":{"type":"Point","coordinates":[-114.9948,35.987389]},"properties":{"id":560,"numid":5634,"stationid":5634,"name":"Black Mountain DB","description":"Water Level Bubbler","in_service":1,"interval_data":"0.31","interval_time":43200,"novascore":1}},{"type":"Feature","geometry":{"type":"Point","coordinates":[-115.162594,36.155764]},"properties":{"id":274,"numid":4289,"stationid":4289,"name":"Freeway Channel near Charleston","description":"Bubbler","in_service":1,"interval_data":"0.43","interval_time":43200,"novascore":1}},{"type":"Feature","geometry":{"type":"Point","coordinates":[-114.62764,35.961]},"properties":{"id":8,"numid":8,"stationid":8,"name":"Willow Beach 8 (NPS)","in_service":1,"interval_data":"0.31","interval_time":43200,"novascore":1}},{"type":"Feature","geometry":{"type":"Point","coordinates":[-114.696322,35.483345]},"properties":{"id":55,"numid":430,"stationid":430,"name":"Access Road Wash (NPS)","in_service":1,"interval_data":"0.12","interval_time":43200,"novascore":1}},{"type":"Feature","geometry":{"type":"Point","coordinates":[-115.112778,36.219778]},"properties":{"id":401,"numid":4524,"stationid":4524,"name":"Cheyenne PB","description":"Water Level Bubbler","in_service":1,"interval_data":"0.35","interval_time":43200,"novascore":1}},{"type":"Feature","geometry":{"type":"Point","coordinates":[-115.24225,36.12975]},"properties":{"id":284,"numid":4309,"stationid":4309,"name":"Desert Inn DB","description":"Water Level Float","in_service":1,"interval_data":"0.35","interval_time":43200,"novascore":1}},{"type":"Feature","geometry":{"type":"Point","coordinates":[-114.324,35.156]},"properties":{"id":879,"numid":1695,"stationid":1695,"name":"Cave Spring (Mohave County)","in_service":1,"interval_data":"0.47","interval_time":43200,"novascore":1}},{"type":"Feature","geometry":{"type":"Point","coordinates":[-113.306111,36.505833]},"properties":{"id":882,"numid":1604,"stationid":1604,"name":"Hurricane Cliffs (Mohave County)","in_service":1,"interval_data":"0.35","interval_time":43200,"novascore":1}},{"type":"Feature","geometry":{"type":"Point","coordinates":[-115.003639,36.02825]},"properties":{"id":416,"numid":4564,"stationid":4564,"name":"Pittman Railroad Channel","description":"Water Level Float","in_service":1,"interval_data":"0.35","interval_time":43200,"novascore":1}},{"type":"Feature","geometry":{"type":"Point","coordinates":[-114.6080556,35.1075]},"properties":{"id":868,"numid":7610,"stationid":7610,"name":"Bullhead City Rain (Mohave County)","in_service":1,"interval_data":"0.12","interval_time":43200,"novascore":1}},{"type":"Feature","geometry":{"type":"Point","coordinates":[-113.84,36.89361111]},"properties":{"id":883,"numid":7516,"stationid":7516,"name":"Figure 4 (Mohave County)","in_service":1,"interval_data":"0.24","interval_time":43200,"novascore":1}},{"type":"Feature","geometry":{"type":"Point","coordinates":[-115.02525,36.091667]},"properties":{"id":446,"numid":4694,"stationid":4694,"name":"Duck Creek at Broadbent","description":"Water Level Float","in_service":1,"interval_data":"0.35","interval_time":43200,"novascore":1}},{"type":"Feature","geometry":{"type":"Point","coordinates":[-115.325075,35.765569]},"properties":{"id":520,"numid":4954,"stationid":4954,"name":"Jean Airport","description":"Weather Station","in_service":1,"interval_data":"0.39","interval_time":43200,"novascore":1}},{"type":"Feature","geometry":{"type":"Point","coordinates":[-115.077778,36.183056]},"properties":{"id":272,"numid":4284,"stationid":4284,"name":"Las Vegas Wash at Lamb","description":"Water Level Bubbler","in_service":1,"interval_data":"0.31","interval_time":43200,"novascore":1}},{"type":"Feature","geometry":{"type":"Point","coordinates":[-115.118094,36.055017]},"properties":{"id":428,"numid":4634,"stationid":4634,"name":"Duck Creek at Eastern","description":"Water Level Float","in_service":1,"interval_data":"0.47","interval_time":43200,"novascore":1}},{"type":"Feature","geometry":{"type":"Point","coordinates":[-115.304028,36.105639]},"properties":{"id":372,"numid":4429,"stationid":4429,"name":"Naples Channel","description":"Water Level Float","in_service":1,"interval_data":"0.39","interval_time":43200,"novascore":1}},{"type":"Feature","geometry":{"type":"Point","coordinates":[-114.158611,35.400833]},"properties":{"id":874,"numid":1500,"stationid":1500,"name":"Cherum Peak (Mohave County)","in_service":1,"interval_data":"0.79","interval_time":43200,"novascore":1}},{"type":"Feature","geometry":{"type":"Point","coordinates":[-114.39,35.22]},"properties":{"id":873,"numid":7600,"stationid":7600,"name":"Union Pass (Mohave County)","in_service":1,"interval_data":"0.51","interval_time":43200,"novascore":1}},{"type":"Feature","geometry":{"type":"Point","coordinates":[-115.083069,36.052353]},"properties":{"id":465,"numid":4739,"stationid":4739,"name":"UPRR Channel","description":"Water Level Float","in_service":1,"interval_data":"0.43","interval_time":43200,"novascore":1}},{"type":"Feature","geometry":{"type":"Point","coordinates":[-114.677806,35.178333]},"properties":{"id":553,"numid":5244,"stationid":5244,"name":"Laughlin 2","description":"Weather Station","in_service":1,"interval_data":"0.24","interval_time":43200,"novascore":1}},{"type":"Feature","geometry":{"type":"Point","coordinates":[-115.417583,36.180639]},"properties":{"id":289,"numid":4329,"stationid":4329,"name":"Brownstone Canyon","description":"Rain Gauge","in_service":1,"interval_data":"1.54","interval_time":43200,"novascore":1}},{"type":"Feature","geometry":{"type":"Point","coordinates":[-115.294306,36.179056]},"properties":{"id":241,"numid":4214,"stationid":4214,"name":"Summerlin Pkwy","description":"Rain Gauge","in_service":1,"interval_data":"0.55","interval_time":43200,"novascore":1}},{"type":"Feature","geometry":{"type":"Point","coordinates":[-114.733917,35.164583]},"properties":{"id":550,"numid":5224,"stationid":5224,"name":"Laughlin 1","description":"Rain Gauge","in_service":1,"interval_data":"0.39","interval_time":43200,"novascore":1}},{"type":"Feature","geometry":{"type":"Point","coordinates":[-114.115,37.286111]},"properties":{"id":864,"numid":1506,"stationid":1506,"name":"Upper Lime Mountain (Mohave County)","in_service":1,"interval_data":"0.43","interval_time":43200,"novascore":1}},{"type":"Feature","geometry":{"type":"Point","coordinates":[-114.172,35.7]},"properties":{"id":850,"numid":7440,"stationid":7440,"name":"Archibald Wash (Mohave County)","in_service":1,"interval_data":"0.28","interval_time":43200,"novascore":1}},{"type":"Feature","geometry":{"type":"Point","coordinates":[-114.409,35.608]},"properties":{"id":872,"numid":1630,"stationid":1630,"name":"Detrital Wash @ SR93 (Mohave County)","in_service":1,"interval_data":"0.24","interval_time":43200,"novascore":1}},{"type":"Feature","geometry":{"type":"Point","coordinates":[-113.920278,37.420278]},"properties":{"id":863,"numid":1508,"stationid":1508,"name":"Bull Valley Mtns  (Mohave County)","in_service":1,"interval_data":"0.00","interval_time":43200,"novascore":1}},{"type":"Feature","geometry":{"type":"Point","coordinates":[-113.844722,37.3025]},"properties":{"id":860,"numid":1507,"stationid":1507,"name":"Pahcoon Flat (Mohave County)","in_service":1,"interval_data":"0.55","interval_time":43200,"novascore":1}},{"type":"Feature","geometry":{"type":"Point","coordinates":[-115.052,36.048694]},"properties":{"id":473,"numid":4759,"stationid":4759,"name":"Pittman Park DB","description":"Water Level Float","in_service":1,"interval_data":"0.43","interval_time":43200,"novascore":1}},{"type":"Feature","geometry":{"type":"Point","coordinates":[-114.908889,35.457611]},"properties":{"id":539,"numid":5124,"stationid":5124,"name":"Searchlight","description":"Rain Gauge","in_service":1,"interval_data":"0.39","interval_time":43200,"novascore":1}},{"type":"Feature","geometry":{"type":"Point","coordinates":[-114.617056,35.883494]},"properties":{"id":42,"numid":350,"stationid":350,"name":"Willow Beach Hwy 93 (NPS)","in_service":1,"interval_data":"0.24","interval_time":43200,"novascore":1}},{"type":"Feature","geometry":{"type":"Point","coordinates":[-115.031069,36.253528]},"properties":{"id":208,"numid":4104,"stationid":4104,"name":"Nellis AFB North","description":"Weather Station","in_service":1,"interval_data":"0.28","interval_time":43200,"novascore":1}},{"type":"Feature","geometry":{"type":"Point","coordinates":[-114.579,35.014]},"properties":{"id":853,"numid":1640,"stationid":1640,"name":"El Rodeo Wash (Mohave County)","in_service":1,"interval_data":"0.27","interval_time":43200,"novascore":1}},{"type":"Feature","geometry":{"type":"Point","coordinates":[-114.497,35.171]},"properties":{"id":851,"numid":1525,"stationid":1525,"name":"Punto de Vista (Mohave County)","in_service":1,"interval_data":"0.39","interval_time":43200,"novascore":1}},{"type":"Feature","geometry":{"type":"Point","coordinates":[-114.543,35.114]},"properties":{"id":852,"numid":1610,"stationid":1610,"name":"Silver Creek Precipitation (Mohave County)","in_service":1,"interval_data":"0.39","interval_time":43200,"novascore":1}},{"type":"Feature","geometry":{"type":"Point","coordinates":[-115.322361,36.058]},"properties":{"id":290,"numid":4334,"stationid":4334,"name":"Upper Flamingo 1","description":"Rain Gauge","in_service":1,"interval_data":"0.31","interval_time":43200,"novascore":1}},{"type":"Feature","geometry":{"type":"Point","coordinates":[-114.379,35.31]},"properties":{"id":875,"numid":1530,"stationid":1530,"name":"Willow Springs Rain (Mohave County)","in_service":1,"interval_data":"0.83","interval_time":43200,"novascore":1}},{"type":"Feature","geometry":{"type":"Point","coordinates":[-114.278,35.585]},"properties":{"id":902,"numid":7470,"stationid":7470,"name":"Dolan Springs (Mohave County)","in_service":1,"interval_data":"0.43","interval_time":43200,"novascore":1}},{"type":"Feature","geometry":{"type":"Point","coordinates":[-114.0647,37.4981]},"properties":{"id":885,"numid":7780,"stationid":7780,"name":"Beaver Dam State Park (Mohave County)","in_service":1,"interval_data":"0.24","interval_time":43200,"novascore":1}},{"type":"Feature","geometry":{"type":"Point","coordinates":[-114.561,34.868]},"properties":{"id":914,"numid":1680,"stationid":1680,"name":"Mohave Valley (Mohave County)","in_service":1,"interval_data":"0.04","interval_time":43200,"novascore":1}},{"type":"Feature","geometry":{"type":"Point","coordinates":[-114.993222,36.144417]},"properties":{"id":231,"numid":4189,"stationid":4189,"name":"Sunrise Landfill 1","description":"Rain Gauge","in_service":1,"interval_data":"0.28","interval_time":43200,"novascore":1}},{"type":"Feature","geometry":{"type":"Point","coordinates":[-115.371489,36.206472]},"properties":{"id":239,"numid":4209,"stationid":4209,"name":"Summerlin NW","description":"Rain Gauge","in_service":1,"interval_data":"1.02","interval_time":43200,"novascore":1}},{"type":"Feature","geometry":{"type":"Point","coordinates":[-114.59625,35.82578]},"properties":{"id":5,"numid":5,"stationid":5,"name":"Householder Pass (NPS)","in_service":1,"interval_data":"0.24","interval_time":43200,"novascore":1}},{"type":"Feature","geometry":{"type":"Point","coordinates":[-113.823,37.053]},"properties":{"id":849,"numid":7561,"stationid":7561,"name":"Scrub Peak (Mohave County)","in_service":1,"interval_data":"0.16","interval_time":43200,"novascore":1}},{"type":"Feature","geometry":{"type":"Point","coordinates":[-115.172444,36.2572]},"properties":{"id":198,"numid":4079,"stationid":4079,"name":"Western Tributary of Las Vegas Wash","description":"Water Level Float","in_service":1,"interval_data":"0.47","interval_time":43200,"novascore":1}},{"type":"Feature","geometry":{"type":"Point","coordinates":[-115.25325,36.225306]},"properties":{"id":258,"numid":4254,"stationid":4254,"name":"Lower Gowan North DB","description":"Water Level Float","in_service":1,"interval_data":"0.63","interval_time":43200,"novascore":1}},{"type":"Feature","geometry":{"type":"Point","coordinates":[-115.252225,36.216942]},"properties":{"id":260,"numid":4259,"stationid":4259,"name":"Gowan South DB","description":"Water Level Bubbler","in_service":1,"interval_data":"0.59","interval_time":43200,"novascore":1}},{"type":"Feature","geometry":{"type":"Point","coordinates":[-114.335,35.733]},"properties":{"id":857,"numid":1535,"stationid":1535,"name":"White Hills Precipitation (Mohave County)","in_service":1,"interval_data":"0.39","interval_time":43200,"novascore":1}},{"type":"Feature","geometry":{"type":"Point","coordinates":[-114.065,36.002]},"properties":{"id":856,"numid":7590,"stationid":7590,"name":"Meadview Rain (Mohave County)","in_service":1,"interval_data":"0.15","interval_time":43200,"novascore":1}},{"type":"Feature","geometry":{"type":"Point","coordinates":[-114.86575,35.968917]},"properties":{"id":496,"numid":4824,"stationid":4824,"name":"Veteran\u0027s DB","description":"Water Level Float","in_service":1,"interval_data":"0.28","interval_time":43200,"novascore":1}},{"type":"Feature","geometry":{"type":"Point","coordinates":[-114.500556,35.253333]},"properties":{"id":963,"numid":7405,"stationid":7405,"name":"Mohave Lakeview (Mohave County)","in_service":1,"interval_data":"0.31","interval_time":43200,"novascore":1}},{"type":"Feature","geometry":{"type":"Point","coordinates":[-114.559722,35.555833]},"properties":{"id":952,"numid":1556,"stationid":1556,"name":"Tufa (Mohave County)","in_service":1,"interval_data":"M","interval_time":43200,"novascore":1}},{"type":"Feature","geometry":{"type":"Point","coordinates":[-114.550278,35.166389]},"properties":{"id":953,"numid":7661,"stationid":7661,"name":"Black Wash (Mohave County)","in_service":1,"interval_data":"0.43","interval_time":43200,"novascore":1}},{"type":"Feature","geometry":{"type":"Point","coordinates":[-115.035769,36.131861]},"properties":{"id":202,"numid":4089,"stationid":4089,"name":"Las Vegas Wash below Vegas Valley Dr. (USGS)","description":"This gauge was relocated downstream of previous site on 6/4/2018, and again on 2/27/2019.","in_service":1,"interval_data":"0.31","interval_time":43200,"novascore":1}},{"type":"Feature","geometry":{"type":"Point","coordinates":[-114.5183333,35.02583333]},"properties":{"id":958,"numid":7404,"stationid":7404,"name":"Fort Mojave (Mohave County)","in_service":1,"interval_data":"0.43","interval_time":43200,"novascore":1}},{"type":"Feature","geometry":{"type":"Point","coordinates":[-114.544,35.098]},"properties":{"id":880,"numid":1620,"stationid":1620,"name":"Montana Wash (Mohave County)","in_service":1,"interval_data":"0.39","interval_time":43200,"novascore":1}},{"type":"Feature","geometry":{"type":"Point","coordinates":[-114.31472222,35.31583333]},"properties":{"id":964,"numid":1503,"stationid":1503,"name":"Mud Spring (Mohave County)","in_service":1,"interval_data":"0.59","interval_time":43200,"novascore":1}},{"type":"Feature","geometry":{"type":"Point","coordinates":[-114.362417,36.439972]},"properties":{"id":127,"numid":3254,"stationid":3254,"name":"Overton Beach","description":"Weather Station","in_service":1,"interval_data":"0.39","interval_time":43200,"novascore":1}},{"type":"Feature","geometry":{"type":"Point","coordinates":[-114.551944,35.820278]},"properties":{"id":951,"numid":7665,"stationid":7665,"name":"CR 143 @ SR 93 (Mohave County)","in_service":1,"interval_data":"0.28","interval_time":43200,"novascore":1}},{"type":"Feature","geometry":{"type":"Point","coordinates":[-114.498889,35.934444]},"properties":{"id":950,"numid":7625,"stationid":7625,"name":"CR 143 @ MP8 (Mohave County)","in_service":1,"interval_data":"0.16","interval_time":43200,"novascore":1}},{"type":"Feature","geometry":{"type":"Point","coordinates":[-114.479,34.776]},"properties":{"id":920,"numid":7420,"stationid":7420,"name":"Golden Shores (Mohave County)","in_service":1,"interval_data":"0.00","interval_time":43200,"novascore":1}},{"type":"Feature","geometry":{"type":"Point","coordinates":[-114.443611,35.061111]},"properties":{"id":956,"numid":1524,"stationid":1524,"name":"Hardy Mountain (Mohave County)","in_service":1,"interval_data":"0.51","interval_time":43200,"novascore":1}},{"type":"Feature","geometry":{"type":"Point","coordinates":[-114.574444,34.96777778]},"properties":{"id":957,"numid":1565,"stationid":1565,"name":"Mesquite Creek (Mohave County)","in_service":1,"interval_data":"0.28","interval_time":43200,"novascore":1}},{"type":"Feature","geometry":{"type":"Point","coordinates":[-115.146992,36.113647]},"properties":{"id":390,"numid":4484,"stationid":4484,"name":"Tropicana Wash at University Center Drive","description":"Water Level Float","in_service":1,"interval_data":"0.48","interval_time":43200,"novascore":1}},{"type":"Feature","geometry":{"type":"Point","coordinates":[-114.58875,35.87789]},"properties":{"id":2,"numid":2,"stationid":2,"name":"Willow Beach 2 (NPS)","in_service":1,"interval_data":"0.28","interval_time":43200,"novascore":1}},{"type":"Feature","geometry":{"type":"Point","coordinates":[-115.098611,36.195833]},"properties":{"id":196,"numid":4074,"stationid":4074,"name":"Las Vegas Wash at Lake Mead","description":"Water Level Bubbler","in_service":1,"interval_data":"0.43","interval_time":43200,"novascore":1}},{"type":"Feature","geometry":{"type":"Point","coordinates":[-114.25416666,35.25472222]},"properties":{"id":966,"numid":1501,"stationid":1501,"name":"Golden Valley  (Mohave County)","in_service":1,"interval_data":"0.31","interval_time":43200,"novascore":1}},{"type":"Feature","geometry":{"type":"Point","coordinates":[-114.62627,35.90058]},"properties":{"id":32,"numid":310,"stationid":310,"name":"Last Chance Hwy 93 (NPS)","in_service":1,"interval_data":"0.24","interval_time":43200,"novascore":1}},{"type":"Feature","geometry":{"type":"Point","coordinates":[-114.253,35.598]},"properties":{"id":878,"numid":7431,"stationid":7431,"name":"Mount Tipton (Mohave County)","in_service":1,"interval_data":"0.16","interval_time":43200,"novascore":1}},{"type":"Feature","geometry":{"type":"Point","coordinates":[-113.928611,36.908889]},"properties":{"id":926,"numid":7570,"stationid":7568,"name":"Beaver Dam (Mohave County)","in_service":1,"interval_data":"0.20","interval_time":43200,"novascore":1}},{"type":"Feature","geometry":{"type":"Point","coordinates":[-114.93975,36.021389]},"properties":{"id":471,"numid":4754,"stationid":4754,"name":"Equestrian DB","description":"Water Level Float","in_service":1,"interval_data":"0.20","interval_time":43200,"novascore":1}},{"type":"Feature","geometry":{"type":"Point","coordinates":[-115.053722,36.142111]},"properties":{"id":1013,"numid":4084,"stationid":4084,"name":"Las Vegas Wash above Flamingo Wash confluence","description":"Water Level Bubbler","in_service":1,"interval_data":"0.28","interval_time":43200,"novascore":1}},{"type":"Feature","geometry":{"type":"Point","coordinates":[-115.237778,36.0075]},"properties":{"id":436,"numid":4649,"stationid":4649,"name":"Duck Creek Railroad DB","description":"Water Level Bubbler","in_service":1,"interval_data":"0.28","interval_time":43200,"novascore":1}},{"type":"Feature","geometry":{"type":"Point","coordinates":[-115.630194,36.249472]},"properties":{"id":1009,"numid":3834,"stationid":3834,"name":"Rainbow Canyon","description":"Rain Gauge","in_service":1,"interval_data":"0.00","interval_time":43200,"novascore":1}},{"type":"Feature","geometry":{"type":"Point","coordinates":[-115.524361,36.266806]},"properties":{"id":1004,"numid":3864,"stationid":3864,"name":"Harris Springs 3","description":"Rain Gauge","in_service":1,"interval_data":"1.10","interval_time":43200,"novascore":1}},{"type":"Feature","geometry":{"type":"Point","coordinates":[-115.061694,36.155028]},"properties":{"id":1018,"numid":4004,"stationid":4004,"name":"Las Vegas Wash at Nellis","description":"Water Level Bubbler","in_service":1,"interval_data":"0.35","interval_time":43200,"novascore":1}},{"type":"Feature","geometry":{"type":"Point","coordinates":[-115.019167,36.1525]},"properties":{"id":1025,"numid":4179,"stationid":4179,"name":"Orchard DB","description":"Water Level Bubbler","in_service":1,"interval_data":"0.28","interval_time":43200,"novascore":1}},{"type":"Feature","geometry":{"type":"Point","coordinates":[-115.087056,36.068889]},"properties":{"id":1032,"numid":4659,"stationid":4659,"name":"Duck Creek above Sunset","description":"Water Level Bubbler","in_service":1,"interval_data":"0.43","interval_time":43200,"novascore":1}},{"type":"Feature","geometry":{"type":"Point","coordinates":[-114.64435,35.874686]},"properties":{"id":40,"numid":340,"stationid":340,"name":"Willow Beach Wash (NPS)","in_service":1,"interval_data":"0.24","interval_time":43200,"novascore":1}},{"type":"Feature","geometry":{"type":"Point","coordinates":[-115.579167,36.228861]},"properties":{"id":1005,"numid":3854,"stationid":3854,"name":"Harris Springs 1","description":"Weather Station","in_service":1,"interval_data":"0.35","interval_time":43200,"novascore":1}},{"type":"Feature","geometry":{"type":"Point","coordinates":[-115.097181,36.278114]},"properties":{"id":1893,"numid":3005000,"stationid":4129,"name":"Vandenberg North DB","description":"Water Level Bubbler (2x)","in_service":1,"interval_data":"0.31","interval_time":43200,"novascore":1}},{"type":"Feature","geometry":{"type":"Point","coordinates":[-114.675,36.656667]},"properties":{"id":1038,"numid":3219,"stationid":3219,"name":"Segmiller Wash","description":"Rain Gauge","in_service":1,"interval_data":"0.31","interval_time":43200,"novascore":1}},{"type":"Feature","geometry":{"type":"Point","coordinates":[-114.684722,36.633889]},"properties":{"id":1042,"numid":3204,"stationid":3204,"name":"Hogan Springs Overlook","description":"Weather Station","in_service":1,"interval_data":"0.20","interval_time":43200,"novascore":1}},{"type":"Feature","geometry":{"type":"Point","coordinates":[-114.073333,36.825556]},"properties":{"id":79,"numid":2594,"stationid":2594,"name":"Town Wash DB","description":"Water Level Float","in_service":1,"interval_data":"0.24","interval_time":43200,"novascore":1}},{"type":"Feature","geometry":{"type":"Point","coordinates":[-114.653314,35.880247]},"properties":{"id":30,"numid":300,"stationid":300,"name":"Last Chance Wash (NPS)","in_service":1,"interval_data":"0.24","interval_time":43200,"novascore":1}},{"type":"Feature","geometry":{"type":"Point","coordinates":[-115.558917,36.239361]},"properties":{"id":1002,"numid":3844,"stationid":3844,"name":"Harris Springs 2","description":"Rain Gauge","in_service":1,"interval_data":"2.36","interval_time":43200,"novascore":1}},{"type":"Feature","geometry":{"type":"Point","coordinates":[-115.648889,35.811389]},"properties":{"id":1276,"numid":5004,"stationid":5004,"name":"Sandy Valley","description":"Weather Station","in_service":1,"interval_data":"0.28","interval_time":43200,"novascore":1}},{"type":"Feature","geometry":{"type":"Point","coordinates":[-115.393833,35.646556]},"properties":{"id":536,"numid":4994,"stationid":4994,"name":"Primm","description":"Weather Station","in_service":1,"interval_data":"0.12","interval_time":43200,"novascore":1}},{"type":"Feature","geometry":{"type":"Point","coordinates":[-114.6605,35.87308]},"properties":{"id":35,"numid":320,"stationid":320,"name":"Last Chance Access Road (NPS)","in_service":1,"interval_data":"0.28","interval_time":43200,"novascore":1}},{"type":"Feature","geometry":{"type":"Point","coordinates":[-115.024333,36.014919]},"properties":{"id":1270,"numid":4752,"stationid":4752,"name":"Horizon Ridge DB","description":"Water Level Bubbler","in_service":1,"interval_data":"0.31","interval_time":43200,"novascore":1}},{"type":"Feature","geometry":{"type":"Point","coordinates":[-114.755,35.49339]},"properties":{"id":9,"numid":11,"stationid":11,"name":"Black Mtn North (NPS)","in_service":1,"interval_data":"0.16","interval_time":43200,"novascore":1}},{"type":"Feature","geometry":{"type":"Point","coordinates":[-114.706,35.49181]},"properties":{"id":12,"numid":14,"stationid":14,"name":"Cottonwood Cove West (NPS)","in_service":1,"interval_data":"0.16","interval_time":43200,"novascore":1}},{"type":"Feature","geometry":{"type":"Point","coordinates":[-114.771611,36.536528]},"properties":{"id":1052,"numid":3129,"stationid":3129,"name":"Moapa SW 2","description":"Rain Gauge","in_service":1,"interval_data":"0.47","interval_time":43200,"novascore":1}},{"type":"Feature","geometry":{"type":"Point","coordinates":[-115.156306,35.967272]},"properties":{"id":1599,"numid":3016900,"stationid":4722,"name":"Pittman North DB","description":"Bubbler","in_service":1,"interval_data":"0.31","interval_time":43200,"novascore":1}},{"type":"Feature","geometry":{"type":"Point","coordinates":[-115.195528,36.302639]},"properties":{"id":1719,"numid":3007200,"stationid":4501,"name":"Park Highlands West DB","description":"Water Level Bubbler","in_service":1,"interval_data":"0.63","interval_time":43200,"novascore":1}},{"type":"Feature","geometry":{"type":"Point","coordinates":[-114.98,36.746667]},"properties":{"id":118,"numid":3214,"stationid":3214,"name":"Elbow Canyon","description":"Weather Station","in_service":1,"interval_data":"0.20","interval_time":43200,"novascore":1}},{"type":"Feature","geometry":{"type":"Point","coordinates":[-115.053192,36.015311]},"properties":{"id":1990,"numid":3041300,"stationid":4701,"name":"Fire Station 97  (4701)","description":"Rain gauge located at Fire Station 97 in Henderson.","in_service":1,"interval_data":"0.47","interval_time":43200,"novascore":1}},{"type":"Feature","geometry":{"type":"Point","coordinates":[-113.992,37.2939]},"properties":{"id":861,"numid":1645,"stationid":1645,"name":"Motoqua (Mohave County)","description":"Located in Utah","in_service":1,"interval_data":"0.91","interval_time":43200,"novascore":1}},{"type":"Feature","geometry":{"type":"Point","coordinates":[-113.983889,36.973889]},"properties":{"id":1998,"numid":7478,"stationid":7478,"name":"Mormon Well  (Mohave County)","in_service":1,"interval_data":"0.43","interval_time":43200,"novascore":1}},{"type":"Feature","geometry":{"type":"Point","coordinates":[-114.695464,36.711122]},"properties":{"id":131,"numid":3264,"stationid":3264,"name":"Muddy River Moapa (USGS)","description":"Upgraded to ALERT 2 10/19/2020. Downgraded to ALERT 1 10/15/2021.","in_service":1,"interval_data":"0.28","interval_time":43200,"novascore":1}},{"type":"Feature","geometry":{"type":"Point","coordinates":[-114.028889,37.1125]},"properties":{"id":2000,"numid":7618,"stationid":1510,"name":"Catclaw Canyon  (Mohave County)","in_service":1,"interval_data":"0.75","interval_time":43200,"novascore":1}},{"type":"Feature","geometry":{"type":"Point","coordinates":[-114.468333,35.702222]},"properties":{"id":2004,"numid":7495,"stationid":7495,"name":"Detrital Wash @ CR145 (Mohave County)","in_service":1,"interval_data":"0.31","interval_time":43200,"novascore":1}},{"type":"Feature","geometry":{"type":"Point","coordinates":[-114.573611,35.654444]},"properties":{"id":2006,"numid":7794,"stationid":7794,"name":"Carl Scrivens (Mohave County)","in_service":1,"interval_data":"0.47","interval_time":43200,"novascore":1}},{"type":"Feature","geometry":{"type":"Point","coordinates":[-114.736,35.48725]},"properties":{"id":10,"numid":12,"stationid":12,"name":"Black Mtn South (NPS)","in_service":1,"interval_data":"0.16","interval_time":43200,"novascore":1}},{"type":"Feature","geometry":{"type":"Point","coordinates":[-114.521389,35.1325]},"properties":{"id":2009,"numid":7678,"stationid":7678,"name":"Secret Pass Canyon Wash (Mohave County)","in_service":1,"interval_data":"0.47","interval_time":43200,"novascore":1}},{"type":"Feature","geometry":{"type":"Point","coordinates":[-114.5625,35.034167]},"properties":{"id":2011,"numid":1515,"stationid":1515,"name":"Sunrise Vistas (Mohave County)","in_service":1,"interval_data":"0.39","interval_time":43200,"novascore":1}},{"type":"Feature","geometry":{"type":"Point","coordinates":[-114.520833,35.581667]},"properties":{"id":2007,"numid":7605,"stationid":7604,"name":"Mt. Perkins (Mohave County)","in_service":1,"interval_data":"0.59","interval_time":43200,"novascore":1}},{"type":"Feature","geometry":{"type":"Point","coordinates":[-114.494167,35.451111]},"properties":{"id":2008,"numid":1649,"stationid":1649,"name":"Lost Cabin Springs (Mohave County)","in_service":1,"interval_data":"0.55","interval_time":43200,"novascore":1}},{"type":"Feature","geometry":{"type":"Point","coordinates":[-114.603361,35.865139]},"properties":{"id":61,"numid":510,"stationid":510,"name":"Willow Beach Hwy. 93 Access Road (NPS)","in_service":1,"interval_data":"0.24","interval_time":43200,"novascore":1}},{"type":"Feature","geometry":{"type":"Point","coordinates":[-113.979722,35.181667]},"properties":{"id":1876,"numid":5104100,"stationid":51041,"name":"Hualapai Foothills (Mohave County)","in_service":1,"interval_data":"M","interval_time":43200,"novascore":1}},{"type":"Feature","geometry":{"type":"Point","coordinates":[-115.0036,36.0393]},"properties":{"id":480,"numid":4774,"stationid":4774,"name":"Borman","description":"Weather Station","in_service":1,"interval_data":"0.31","interval_time":43200,"novascore":1}},{"type":"Feature","geometry":{"type":"Point","coordinates":[-115.428,36.1305]},"properties":{"id":288,"numid":4324,"stationid":4324,"name":"Red Rock Canyon","description":"Rain Gauge A2","in_service":1,"interval_data":"1.26","interval_time":43200,"novascore":1}},{"type":"Feature","geometry":{"type":"Point","coordinates":[-114.443528,36.556944]},"properties":{"id":2032,"numid":3012300,"stationid":3299,"name":"Muddy River at Cooper St.","description":"Water Level Radar","in_service":1,"interval_data":"0.12","interval_time":43200,"novascore":1}},{"type":"Feature","geometry":{"type":"Point","coordinates":[-115.0246,36.290053]},"properties":{"id":2048,"numid":3005700,"stationid":4139,"name":"Speedway #2 DB","description":"Water Level Bubbler","in_service":1,"interval_data":"0.35","interval_time":43200,"novascore":1}},{"type":"Feature","geometry":{"type":"Point","coordinates":[-115.358972,36.193917]},"properties":{"id":2163,"numid":3043200,"stationid":4201,"name":"Grand Park DB  (4201)","description":"50388 with Amazon Water Level Bubbler","in_service":1,"interval_data":"1.02","interval_time":43200,"novascore":1}},{"type":"Feature","geometry":{"type":"Point","coordinates":[-115.111028,35.9995]},"properties":{"id":2125,"numid":3042000,"stationid":4702,"name":"Fire Station 98  (4702)","in_service":1,"interval_data":"0.04","interval_time":43200,"novascore":1}},{"type":"Feature","geometry":{"type":"Point","coordinates":[-115.373131,36.173353]},"properties":{"id":2141,"numid":3047800,"stationid":4203,"name":"Summerlin DB (DB 5)  (4203)","description":"50388 with Amazon Water Level Bubbler","in_service":1,"interval_data":"0.98","interval_time":43200,"novascore":1}},{"type":"Feature","geometry":{"type":"Point","coordinates":[-114.571306,36.663417]},"properties":{"id":2040,"numid":3012400,"stationid":3269,"name":"Muddy River at Glendale Bridge","description":"Water Level Radar","in_service":1,"interval_data":"0.20","interval_time":43200,"novascore":1}},{"type":"Feature","geometry":{"type":"Point","coordinates":[-114.69888,35.495]},"properties":{"id":53,"numid":420,"stationid":420,"name":"NPS Staff Housing Wash (NPS)","in_service":1,"interval_data":"0.00","interval_time":43200,"novascore":1}},{"type":"Feature","geometry":{"type":"Point","coordinates":[-114.958908,36.042769]},"properties":{"id":486,"numid":4784,"stationid":4784,"name":"C-1 Channel at Warm Springs (USGS)","in_service":1,"interval_data":"0.12","interval_time":43200,"novascore":1}},{"type":"Feature","geometry":{"type":"Point","coordinates":[-115.199756,36.012342]},"properties":{"id":2180,"numid":3020400,"stationid":4651,"name":"Silverado Ranch DB  (4651)","description":"50388 with Amazon Water Level Bubbler","in_service":1,"interval_data":"0.47","interval_time":43200,"novascore":1}},{"type":"Feature","geometry":{"type":"Point","coordinates":[-115.07775,35.939417]},"properties":{"id":459,"numid":4724,"stationid":4724,"name":"Anthem DB","description":"Water Level Bubbler","in_service":1,"interval_data":"0.39","interval_time":43200,"novascore":1}},{"type":"Feature","geometry":{"type":"Point","coordinates":[-115.075361,36.083722]},"properties":{"id":444,"numid":4684,"stationid":4684,"name":"Duck Creek above Mountain Vista","description":"Water Level Bubbler","in_service":1,"interval_data":"0.39","interval_time":43200,"novascore":1}},{"type":"Feature","geometry":{"type":"Point","coordinates":[-114.627333,35.878333]},"properties":{"id":38,"numid":330,"stationid":330,"name":"Willow Beach 330 (NPS)","in_service":1,"interval_data":"0.28","interval_time":43200,"novascore":1}},{"type":"Feature","geometry":{"type":"Point","coordinates":[-115.331556,36.319139]},"properties":{"id":1538,"numid":3005600,"stationid":4584,"name":"Skye Canyon 2 DB  (4584)","description":"Water Level Bubbler","in_service":1,"interval_data":"0.67","interval_time":43200,"novascore":1}},{"type":"Feature","geometry":{"type":"Point","coordinates":[-115.331578,36.311292]},"properties":{"id":1258,"numid":4579,"stationid":4579,"name":"Skye Canyon 1 DB","description":"Water Level Bubbler","in_service":1,"interval_data":"0.59","interval_time":43200,"novascore":1}},{"type":"Feature","geometry":{"type":"Point","coordinates":[-115.181778,36.119333]},"properties":{"id":1101,"numid":4386,"stationid":4389,"name":"Rio (Twain) Pump Site","description":"Originally a CCPW site.  CCRFCD upgraded and assumed site on August 31, 2016.","in_service":1,"interval_data":"0.39","interval_time":43200,"novascore":1}},{"type":"Feature","geometry":{"type":"Point","coordinates":[-114.449,36.758417]},"properties":{"id":107,"numid":3044,"stationid":3044,"name":"Mormon Mesa 1","description":"Rain Gauge","in_service":1,"interval_data":"0.16","interval_time":43200,"novascore":1}},{"type":"Feature","geometry":{"type":"Point","coordinates":[-115.432472,36.428139]},"properties":{"id":163,"numid":3949,"stationid":3949,"name":"Corn Creek NW","description":"Rain Gauge","in_service":1,"interval_data":"0.67","interval_time":43200,"novascore":1}},{"type":"Feature","geometry":{"type":"Point","coordinates":[-114.906111,36.024444]},"properties":{"id":490,"numid":4799,"stationid":4799,"name":"East C-1 DB","description":"Water Level Bubbler","in_service":1,"interval_data":"0.24","interval_time":43200,"novascore":1}},{"type":"Feature","geometry":{"type":"Point","coordinates":[-115.396702,36.205561]},"properties":{"id":2256,"numid":3047600,"stationid":4207,"name":"WOTUS 5 Channel  (4207)","description":"Rain Gauge","in_service":1,"interval_data":"1.69","interval_time":43200,"novascore":1}},{"type":"Feature","geometry":{"type":"Point","coordinates":[-114.576,35.74642]},"properties":{"id":7,"numid":7,"stationid":7,"name":"Eldorado (NPS)","description":"12/03/2020 - station converted from a rain only site to a repeater/rain station.  Added battery voltage point id of 128 and added rain id of 120 but still going to write rain tips to the old id of 7.","in_service":1,"interval_data":"0.12","interval_time":43200,"novascore":1}},{"type":"Feature","geometry":{"type":"Point","coordinates":[-115.421056,36.339083]},"properties":{"id":158,"numid":3929,"stationid":3929,"name":"Grapevine Springs 1","description":"Rain Gauge","in_service":1,"interval_data":"0.59","interval_time":43200,"novascore":1}},{"type":"Feature","geometry":{"type":"Point","coordinates":[-114.621486,35.859597]},"properties":{"id":63,"numid":520,"stationid":520,"name":"Willow Beach Jumbo Wash (NPS)","in_service":1,"interval_data":"0.24","interval_time":43200,"novascore":1}},{"type":"Feature","geometry":{"type":"Point","coordinates":[-114.747,35.45042]},"properties":{"id":11,"numid":13,"stationid":13,"name":"Bill Gays Butte (NPS)","in_service":1,"interval_data":"0.24","interval_time":43200,"novascore":1}},{"type":"Feature","geometry":{"type":"Point","coordinates":[-114.196,35.344]},"properties":{"id":929,"numid":1540,"stationid":1540,"name":"Cerbat Landfill (Mohave County)","description":"Full name - Cerbat Municipal Solid Waste Landfill.  Former name - Santa Claus.  Site will be upgraded to incorporate RH/AT sensors (CY 2025?).","in_service":1,"interval_data":"0.39","interval_time":43200,"novascore":1}},{"type":"Feature","geometry":{"type":"Point","coordinates":[-114.076139,36.707972]},"properties":{"id":90,"numid":2754,"stationid":2754,"name":"Bunkerville","description":"Weather Station","in_service":1,"interval_data":"0.00","interval_time":43200,"novascore":1}},{"type":"Feature","geometry":{"type":"Point","coordinates":[-114.466389,36.613333]},"properties":{"id":2504,"numid":3014300,"stationid":3289,"name":"Fairgrounds DB  (3289)","description":"50388 with Amazon Bubbler","in_service":1,"interval_data":"0.20","interval_time":43200,"novascore":1}},{"type":"Feature","geometry":{"type":"Point","coordinates":[-114.729117,35.485506]},"properties":{"id":51,"numid":410,"stationid":410,"name":"Cottonwood Cove Central (NPS)","in_service":1,"interval_data":"0.16","interval_time":43200,"novascore":1}},{"type":"Feature","geometry":{"type":"Point","coordinates":[-115.029083,35.788889]},"properties":{"id":499,"numid":4834,"stationid":30500,"name":"Boulder City SW  (4834)","description":"Weather Station","in_service":1,"interval_data":"0.00","interval_time":43200,"novascore":1}},{"type":"Feature","geometry":{"type":"Point","coordinates":[-114.011692,35.275858]},"properties":{"id":1681,"numid":5103900,"stationid":51039,"name":"Grace Neil at Bank Street (Mohave County)","description":"Pressure Transducer","in_service":1,"interval_data":"M","interval_time":43200,"novascore":1}},{"type":"Feature","geometry":{"type":"Point","coordinates":[-113.808889,35.485833]},"properties":{"id":1878,"numid":5104700,"stationid":51047,"name":"Antares  (Mohave County)","description":"Old ID 7565","in_service":1,"interval_data":"M","interval_time":43200,"novascore":1}},{"type":"Feature","geometry":{"type":"Point","coordinates":[-115.029289,35.404175]},"properties":{"id":545,"numid":5144,"stationid":5144,"name":"Searchlight SW","description":"Weather Station","in_service":1,"interval_data":"0.35","interval_time":43200,"novascore":1}},{"type":"Feature","geometry":{"type":"Point","coordinates":[-115.163333,36.52]},"properties":{"id":160,"numid":3934,"stationid":3934,"name":"Yucca Forest 2","description":"Weather Station","in_service":1,"interval_data":"0.00","interval_time":43200,"novascore":1}},{"type":"Feature","geometry":{"type":"Point","coordinates":[-115.106861,36.060667]},"properties":{"id":442,"numid":4674,"stationid":4674,"name":"Duck Creek near Tomiyasu","description":"Water Level Float. Upgraded to A2 3/28/2023.","in_service":1,"interval_data":"0.47","interval_time":43200,"novascore":1}},{"type":"Feature","geometry":{"type":"Point","coordinates":[-115.021083,36.044]},"properties":{"id":477,"numid":4769,"stationid":4769,"name":"Pioneer DB","description":"Water Level Bubbler","in_service":1,"interval_data":"0.35","interval_time":43200,"novascore":1}},{"type":"Feature","geometry":{"type":"Point","coordinates":[-115.003583,36.140889]},"properties":{"id":228,"numid":4184,"stationid":4184,"name":"Sunrise Landfill 2","description":"Weather Station","in_service":1,"interval_data":"0.28","interval_time":43200,"novascore":1}}]}