{
  "p": {
    "value": [
      930.0,
      925.0,
      921.0,
      909.0,
      903.0,
      898.0,
      895.0,
      878.0,
      850.0,
      848.0,
      821.0,
      811.0,
      791.0,
      782.0,
      772.0,
      762.0,
      728.0,
      721.0,
      719.0,
      711.0,
      703.0,
      700.0,
      694.0,
      660.0,
      652.0,
      645.0,
      638.0,
      622.0,
      613.0,
      599.0,
      579.0,
      578.0,
      572.0,
      548.0,
      538.0,
      534.0,
      525.0,
      518.0,
      512.0,
      500.0,
      495.0,
      460.0,
      455.0,
      449.0,
      443.0,
      432.0,
      427.0,
      423.0,
      412.0,
      409.0,
      400.0,
      392.0,
      387.0,
      373.0,
      355.0,
      347.0,
      345.0,
      339.0,
      321.0,
      308.0,
      300.0,
      290.0,
      286.0,
      264.0,
      250.0,
      249.0,
      245.0,
      222.0,
      203.0,
      200.0,
      194.0,
      188.0,
      185.0,
      184.0,
      177.0,
      175.0,
      165.0,
      158.0,
      150.0,
      149.0,
      148.0,
      136.0,
      135.0,
      131.0,
      130.0,
      128.0,
      123.0,
      118.0,
      115.0,
      114.0,
      112.0,
      110.0,
      109.0,
      104.0,
      102.0,
      100.0
    ],
    "unit": "hectopascal"
  },
  "z": {
    "value": [
      697.0,
      742.0,
      780.0,
      895.0,
      954.0,
      1002.0,
      1031.0,
      1199.0,
      1481.0,
      1501.0,
      1776.0,
      1880.0,
      2093.0,
      2190.0,
      2299.0,
      2410.0,
      2798.0,
      2880.0,
      2903.0,
      2996.0,
      3090.0,
      3126.0,
      3195.0,
      3601.0,
      3699.0,
      3787.0,
      3875.0,
      4080.0,
      4197.0,
      4384.0,
      4658.0,
      4672.0,
      4753.0,
      5087.0,
      5230.0,
      5287.0,
      5417.0,
      5520.0,
      5609.0,
      5790.0,
      5866.0,
      6418.0,
      6499.0,
      6598.0,
      6698.0,
      6885.0,
      6971.0,
      7041.0,
      7234.0,
      7288.0,
      7450.0,
      7594.0,
      7685.0,
      7947.0,
      8298.0,
      8460.0,
      8502.0,
      8622.0,
      8996.0,
      9280.0,
      9460.0,
      9689.0,
      9783.0,
      10317.0,
      10680.0,
      10706.0,
      10810.0,
      11441.0,
      12015.0,
      12110.0,
      12302.0,
      12500.0,
      12601.0,
      12636.0,
      12881.0,
      12953.0,
      13326.0,
      13601.0,
      13930.0,
      13973.0,
      14016.0,
      14554.0,
      14601.0,
      14793.0,
      14841.0,
      14940.0,
      15193.0,
      15457.0,
      15619.0,
      15674.0,
      15786.0,
      15900.0,
      15957.0,
      16253.0,
      16375.0,
      16500.0
    ],
    "unit": "meter"
  },
  "T": {
    "value": [
      25.4,
      26.8,
      26.6,
      25.9,
      25.6,
      25.6,
      25.4,
      24.0,
      21.8,
      21.6,
      19.6,
      18.8,
      17.2,
      16.4,
      15.6,
      14.8,
      11.8,
      11.2,
      11.0,
      10.2,
      9.3,
      9.0,
      8.3,
      4.4,
      3.5,
      2.7,
      1.8,
      -0.1,
      -1.3,
      -3.1,
      -5.7,
      -5.8,
      -6.5,
      -9.1,
      -10.4,
      -10.9,
      -11.9,
      -12.7,
      -13.3,
      -14.7,
      -15.1,
      -16.5,
      -17.2,
      -18.0,
      -18.8,
      -20.4,
      -21.1,
      -21.7,
      -23.1,
      -23.5,
      -24.9,
      -26.2,
      -27.0,
      -29.3,
      -32.5,
      -33.9,
      -34.3,
      -35.3,
      -38.3,
      -40.6,
      -42.1,
      -44.1,
      -44.9,
      -47.2,
      -48.7,
      -48.9,
      -49.5,
      -53.2,
      -56.5,
      -57.1,
      -57.7,
      -58.3,
      -58.5,
      -58.2,
      -56.3,
      -55.7,
      -56.7,
      -57.5,
      -55.7,
      -55.7,
      -55.7,
      -56.4,
      -56.5,
      -56.1,
      -56.0,
      -55.9,
      -56.8,
      -57.7,
      -58.3,
      -57.7,
      -57.5,
      -57.8,
      -58.0,
      -58.8,
      -59.1,
      -59.5
    ],
    "unit": "degree_Celsius"
  },
  "Td": {
    "value": [
      -0.6,
      1.8,
      1.6,
      0.9,
      0.6,
      -0.4,
      -0.5,
      -0.7,
      -1.2,
      -1.3,
      -2.4,
      -2.8,
      -3.6,
      -4.0,
      -4.5,
      -4.9,
      -6.5,
      -6.8,
      -6.8,
      -6.9,
      -7.0,
      -7.0,
      -7.2,
      -8.1,
      -8.3,
      -8.5,
      -8.7,
      -9.1,
      -9.4,
      -9.8,
      -10.4,
      -10.6,
      -11.9,
      -17.1,
      -17.0,
      -16.9,
      -19.9,
      -22.4,
      -24.4,
      -28.7,
      -30.1,
      -44.5,
      -44.4,
      -44.3,
      -44.1,
      -43.9,
      -43.8,
      -43.7,
      -46.7,
      -47.5,
      -47.9,
      -48.2,
      -48.4,
      -49.0,
      -49.8,
      -50.2,
      -50.3,
      -50.9,
      -52.8,
      -54.2,
      -55.1,
      -56.4,
      -56.9,
      -62.7,
      -66.7,
      -66.9,
      -67.1,
      -68.6,
      -69.9,
      -70.1,
      -70.7,
      -71.3,
      -72.5,
      -72.5,
      -72.7,
      -72.7,
      -77.2,
      -80.5,
      -81.7,
      -82.7,
      -83.7,
      -86.3,
      -86.5,
      -86.1,
      -86.0,
      -85.9,
      -86.3,
      -86.7,
      -87.3,
      -87.7,
      -87.5,
      -87.7,
      -87.7,
      -88.2,
      -88.3,
      -88.5
    ],
    "unit": "degree_Celsius"
  },
  "u": {
    "value": [
      1.0000000000000009,
      -7.66044443118978,
      -7.66044443118978,
      -8.35623892592501,
      -7.210533048740758,
      -6.101049646137003,
      -5.472322293210699,
      -11.471528727020921,
      -11.49066664678467,
      -11.49066664678467,
      -2.394141003279681,
      2.9583278321848945,
      3.5355339059327386,
      1.3680805733026744,
      -0.0,
      -0.0,
      -0.0,
      -0.0,
      -0.0,
      -1.8117333157176452,
      0.5229344564859499,
      1.552914270615124,
      -0.520944533000791,
      -1.9318516525781366,
      -0.5209445330007908,
      -1.9999999999999998,
      0.3486229709906318,
      -1.2678547852220985,
      -3.8637033051562732,
      -1.9999999999999998,
      -7.417470836534299,
      -7.517540966287267,
      -5.656854249492381,
      -1.7542302283364197,
      -0.43577871373829097,
      -0.8682408883346514,
      -2.0521208599540133,
      -8.572527594031472e-16,
      -3.380946093925596,
      -8.572527594031472e-16,
      0.41853884246475165,
      1.1471528727020923,
      0.6427876096865393,
      -0.9961946980917455,
      -0.0,
      -2.8190778623577253,
      -0.845236523481399,
      -1.0598385284664098,
      -2.298133329356934,
      -2.1580194010159532,
      -2.86788218175523,
      -1.690473046962798,
      -2.2943057454041837,
      -0.6945927106677211,
      -1.7101007166283444,
      1.0418890660015827,
      0.41853884246475165,
      -1.5529142706151262,
      0.8715574274765794,
      -2.394141003279682,
      -1.102182119232618e-15,
      0.9587131702242374,
      3.1058285412302498,
      17.38666487320323,
      26.079997309804845,
      26.30799174920135,
      27.893451546568876,
      20.0,
      17.726539554219745,
      19.318516525781366,
      20.082399875223743,
      20.673237657289985,
      16.929123959578988,
      15.58845726811989,
      12.855752193730785,
      14.849242404917497,
      25.37170076121953,
      13.022755533022625,
      22.65769467591625,
      23.49231551964771,
      22.825356391083684,
      6.893654271085457,
      7.989036278036591,
      10.125553387976844,
      10.39230484541326,
      12.474091338637148,
      18.79385241571817,
      14.672214011007084,
      10.286007608425347,
      8.66811828967394,
      5.66388351944854,
      2.9583278321848945,
      -0.34862297099063266,
      -4.898587196589413e-16,
      -1.1471528727020919,
      0.7764571353075624
    ],
    "unit": "knot"
  },
  "v": {
    "value": [
      -1.7320508075688767,
      -6.427876096865393,
      -6.427876096865393,
      -9.958577760546714,
      -12.000342209829572,
      -13.703181864639014,
      -15.035081932574535,
      -16.383040885779835,
      -9.64181414529809,
      -9.64181414529809,
      -6.5778483455013586,
      -6.34415450925655,
      -3.535533905932737,
      -3.7587704831436337,
      -6.0,
      -6.0,
      -9.0,
      -8.0,
      -8.0,
      -6.761480784023478,
      -5.977168188550474,
      -5.79555495773441,
      -2.954423259036624,
      0.5176380902050417,
      2.954423259036624,
      3.464101615137755,
      3.984778792366982,
      2.7189233611099497,
      1.0352761804100834,
      3.464101615137755,
      2.9968527473272966,
      2.7361611466053497,
      5.65685424949238,
      5.737828535778213,
      4.9809734904587275,
      4.92403876506104,
      5.63815572471545,
      7.0,
      7.2504622962931995,
      7.0,
      5.985384301558945,
      1.6383040885779836,
      0.766044443118978,
      -0.08715574274765814,
      -0.0,
      1.0260604299770062,
      1.8126155740732999,
      1.696096192312852,
      1.9283628290596182,
      2.083975111376992,
      4.0957602214449595,
      3.6252311481465997,
      3.2766081771559676,
      3.939231012048832,
      4.698463103929542,
      5.908846518073248,
      5.985384301558945,
      5.795554957734409,
      9.961946980917455,
      6.5778483455013586,
      9.0,
      10.9581416790092,
      11.59110991546882,
      4.6587428118453715,
      6.988114217768057,
      6.073678467284362,
      2.440360796934431,
      3.673940397442059e-15,
      3.125667198004746,
      5.176380902050413,
      6.139805799177479,
      7.524443153164708,
      8.625819495051392,
      9.000000000000007,
      15.32088886237956,
      14.8492424049175,
      9.23454386979305,
      10.927389364671171,
      10.56545654351748,
      8.550503583141714,
      7.4164078649987415,
      -1.2155372436685097,
      -0.41868764994355157,
      4.298042413382012,
      6.000000000000005,
      6.355866996353657,
      6.8404028665133705,
      -3.118675362266391,
      -6.180456898920649,
      -6.7722762285822435,
      -6.9943136531127355,
      -6.34415450925655,
      -3.984778792366982,
      4.0,
      1.6383040885779838,
      2.897777478867205
    ],
    "unit": "knot"
  },
  "site_info": {
    "site-id": "KVEF",
    "site-name": "LAS VEGAS",
    "site-lctn": "NV US",
    "site-latlon": [
      36.05,
      -115.18
    ],
    "site-elv": 697.0,
    "source": "RAOB OBSERVED PROFILE",
    "model": "no-model",
    "fcst-hour": "no-fcst-hour",
    "run-time": [
      "none",
      "none",
      "none",
      "none"
    ],
    "valid-time": [
      2023,
      6,
      4,
      12
    ]
  },
  "titles": {
    "top_title": "RAOB OBSERVED VERTICAL PROFILE",
    "left_title": "VALID: 6-4-2023 12Z",
    "right_title": "KVEF - LAS VEGAS, NV US | 36.05, -115.18    "
  }
}